{
	"forenames": {
		"Adam": 170,
		"Adolf": 2,
		"Adrian": 3,
		"Adrien": 2,
		"Alan": 2,
		"Albert": 7,
		"Ales": 42,
		"Alex": 22,
		"Alexandr": 10,
		"Alexei": 1,
		"Alois": 1,
		"Alzbeta": 1,
		"Andre": 1,
		"Andreas": 1,
		"Andrej": 8,
		"Andrew": 1,
		"André": 1,
		"Angel": 1,
		"Anna Karolína": 1,
		"Antonin": 13,
		"Antonín": 14,
		"Arber": 1,
		"Arkadiy": 1,
		"Artur": 1,
		"Bara": 1,
		"Barnabas": 1,
		"Bastian": 1,
		"Bedrich": 4,
		"Ben": 2,
		"Benjamin": 6,
		"Bogdan": 1,
		"Bohdan": 2,
		"Bohumil": 3,
		"Bohuslav": 3,
		"Braidan": 1,
		"Bretislav": 1,
		"Bronislav": 1,
		"Bruno": 2,
		"Bryan": 1,
		"Calvin": 1,
		"Cenek": 2,
		"Christian": 2,
		"Christopher": 1,
		"Ctibor": 1,
		"Cyril": 1,
		"Dalibor": 5,
		"Dalimil": 1,
		"Damian": 1,
		"Dan": 5,
		"Daniel": 117,
		"Danny": 2,
		"Darek": 3,
		"David": 228,
		"Denis": 29,
		"Dennis": 2,
		"Dieter": 1,
		"Dmitrij": 1,
		"Dominick": 2,
		"Dominik": 128,
		"Dominik Petr": 1,
		"Dorco": 1,
		"Dusan": 6,
		"Dário": 1,
		"Eduard": 4,
		"Elias": 3,
		"Ellen": 1,
		"Emil": 3,
		"Eric": 1,
		"Erik": 12,
		"Ernest": 2,
		"Evzen": 1,
		"Fabien": 1,
		"Felix": 1,
		"Ferdinand": 1,
		"Filip": 130,
		"Florian": 1,
		"Frantisek": 39,
		"Gabriel": 1,
		"Hana": 2,
		"Hanus": 1,
		"Henryk": 1,
		"Hubert": 1,
		"Hugo": 1,
		"Hynek": 7,
		"Igor": 2,
		"Ilja": 1,
		"Imrich": 1,
		"Ivan": 18,
		"Ivo": 5,
		"Jachym": 10,
		"Jack Dylan": 1,
		"Jacob": 2,
		"Jaden": 1,
		"Jakob": 1,
		"Jakub": 292,
		"Jakub Miroslav": 1,
		"Jan": 307,
		"Jannik": 1,
		"Jaromir": 6,
		"Jaromír": 6,
		"Jaroslav": 44,
		"Jens": 1,
		"Jindrich": 9,
		"Jiri": 99,
		"Jirí": 38,
		"Johannes": 1,
		"John": 1,
		"Jonas": 15,
		"Jonás": 1,
		"Josef": 62,
		"Joshua James": 2,
		"Jozef": 2,
		"Juraj": 1,
		"Jáchym": 1,
		"Ján": 3,
		"Kacper": 1,
		"Kamil": 9,
		"Karel": 35,
		"Karol": 1,
		"Karolina": 1,
		"Kelly": 1,
		"Kevin": 4,
		"Klaus": 1,
		"Klára": 1,
		"Kristian": 5,
		"Krystof": 32,
		"Krzysztof": 1,
		"Kyung": 1,
		"Ladislav": 29,
		"Leo": 2,
		"Leon": 2,
		"Leos": 1,
		"Libor": 13,
		"Louis": 1,
		"Lubomir": 1,
		"Lubomír": 5,
		"Lubor": 1,
		"Lubos": 12,
		"Lucas": 1,
		"Lucian": 1,
		"Lucie": 1,
		"Ludek": 6,
		"Ludvik": 1,
		"Ludvik Ivan": 1,
		"Lukas": 149,
		"Luke": 1,
		"Lukás": 35,
		"Maik": 1,
		"Marc": 2,
		"Marcel": 12,
		"Marek": 107,
		"Marian": 6,
		"Mario": 2,
		"Mark": 1,
		"Marko": 1,
		"Martin": 208,
		"Matej": 153,
		"Mathias": 4,
		"Matous": 15,
		"Matous Jan": 1,
		"Matteo": 2,
		"Matthew": 2,
		"Matthias": 2,
		"Matyas": 95,
		"Matyás": 1,
		"Max": 10,
		"Maxim": 3,
		"Maximilián": 1,
		"Maxmilian": 3,
		"Maxmilián": 2,
		"Melichar": 1,
		"Melvin": 1,
		"Michael": 28,
		"Michaela": 1,
		"Michal": 134,
		"Mikhail": 2,
		"Mikulas": 12,
		"Milan": 47,
		"Milos": 5,
		"Miloslav": 9,
		"Miroslav": 43,
		"Mojmir": 1,
		"Nesim": 1,
		"Nicholas": 2,
		"Nick": 3,
		"Nico": 2,
		"Nicolas": 8,
		"Nikita": 2,
		"Nikola": 1,
		"Nikolai": 2,
		"Nikolas": 4,
		"Noah": 1,
		"Olaf": 1,
		"Oldrich": 4,
		"Oliver": 15,
		"OndYej": 1,
		"Ondrej": 145,
		"Oscar": 1,
		"Oskar": 2,
		"Ostap": 1,
		"Otakar": 3,
		"Oto": 2,
		"Otto": 2,
		"Patrik": 71,
		"Patryk": 1,
		"Pavel": 88,
		"Pavol": 3,
		"Pepino": 1,
		"Peter": 1,
		"Petr": 198,
		"Philip": 2,
		"Premysl": 3,
		"Radan": 1,
		"Radek": 61,
		"Radim": 30,
		"Radko": 2,
		"Radomír": 1,
		"Radoslav": 3,
		"Radovan": 5,
		"Rastislav": 1,
		"Rene": 6,
		"René": 6,
		"Richard": 28,
		"Robbie": 1,
		"Robert": 23,
		"Robin": 18,
		"Roman": 50,
		"Ronald": 1,
		"Ronny": 1,
		"Rostislav": 8,
		"Rudolf": 7,
		"Samir": 1,
		"Samuel": 26,
		"Sava": 1,
		"Sean": 1,
		"Sebastian": 17,
		"Segal": 1,
		"Simon": 57,
		"Simon Alex": 1,
		"Slavomir": 3,
		"Stanislav": 20,
		"Stefan": 4,
		"Stepan": 51,
		"Stepán": 2,
		"Steven": 1,
		"Tadeas": 31,
		"Tadeás": 2,
		"Tarik": 1,
		"Teodor": 1,
		"Theodor": 2,
		"Thomas": 2,
		"Tibor": 2,
		"Tim": 1,
		"Timo": 1,
		"Timofej": 1,
		"Timon": 1,
		"Tobby": 1,
		"Tobias": 31,
		"Tobiás": 2,
		"Tom": 3,
		"Tomas": 211,
		"Tommy": 1,
		"Tomás": 61,
		"Tristan": 1,
		"Vaclav": 41,
		"Valdemar": 1,
		"Valentyn": 1,
		"Vashek": 2,
		"Vasyl": 1,
		"Vendula": 1,
		"Viktor": 22,
		"Vilem": 1,
		"Viliam": 1,
		"Vincenc": 1,
		"Vincent": 2,
		"Vit": 16,
		"Vitek": 5,
		"Vitezslav": 4,
		"Vladimir": 12,
		"Vladimír": 19,
		"Vladislav": 4,
		"Vlastimil": 11,
		"Vojta": 1,
		"Vojtech": 108,
		"Vojtěch": 1,
		"Volodymyr": 1,
		"Vratislav": 3,
		"Václav": 25,
		"Vít": 4,
		"Vítezslav": 1,
		"Werner": 2,
		"William": 3,
		"Zbynek": 10,
		"Zdenek": 29,
		"Zdenko": 1,
		"Zoran": 1
	},
	"surnames": {
		"Abdul": 1,
		"Abraham": 2,
		"Adam": 3,
		"Adamec": 5,
		"Adamek": 3,
		"Adamkov": 1,
		"Adamský": 1,
		"Adámek": 2,
		"Albrecht": 1,
		"Alscher": 1,
		"Altrichter": 2,
		"Ambroz": 1,
		"Anastazovsky": 1,
		"Andel": 1,
		"Andrejko": 1,
		"Andres": 1,
		"Andrle": 3,
		"Andrushchenko": 1,
		"Angr": 1,
		"Antal": 1,
		"Anton": 1,
		"Antonicek": 1,
		"Antony": 1,
		"Antos": 1,
		"Apolenar": 2,
		"Appelt": 1,
		"Arnost": 2,
		"Aschenbrenner": 2,
		"Aubrecht": 1,
		"Augustin": 1,
		"Aulicky": 1,
		"Babis": 1,
		"Babka": 2,
		"Bachor": 1,
		"Bachánek": 2,
		"Backovsky": 1,
		"Baco": 1,
		"Badinka": 2,
		"Badoucek": 1,
		"Bahula": 1,
		"Bajak": 1,
		"Bajer": 1,
		"Bajgar": 1,
		"Bajtek": 1,
		"Bakula": 2,
		"Balak": 1,
		"Balatka": 1,
		"Balaz": 1,
		"Baldik": 1,
		"Balek": 1,
		"Balik": 1,
		"Balog": 1,
		"Bambula": 2,
		"Bar": 1,
		"Barabosz": 1,
		"Barak": 1,
		"Baranek": 3,
		"Barcak": 1,
		"Barda": 1,
		"Bares": 4,
		"Barica": 1,
		"Barinka": 5,
		"Barna": 1,
		"Baros": 1,
		"Barta": 4,
		"Bartak": 1,
		"Barteczek": 1,
		"Bartejs": 1,
		"Bartes": 1,
		"Bartko": 2,
		"Barton": 4,
		"Bartonek": 1,
		"Bartos": 7,
		"Bartosak": 3,
		"Bartovic": 2,
		"Bartuska": 1,
		"Barva": 1,
		"Barvir": 1,
		"Baránek": 1,
		"Basta": 1,
		"Bata": 1,
		"Bauer": 1,
		"Bebelak": 1,
		"Beca": 1,
		"Becher": 1,
		"Becvar": 1,
		"Bednar": 5,
		"Bednarik": 4,
		"Bednarík": 1,
		"Behal": 1,
		"Behula": 1,
		"Bejcek": 1,
		"Bejsak": 1,
		"Belohlav": 2,
		"Belohlavek": 1,
		"Belohorsky": 1,
		"Benak": 1,
		"Benda": 3,
		"Bende": 1,
		"Benes": 7,
		"Benisek": 1,
		"Benysek": 1,
		"Benák": 3,
		"Benýsek": 1,
		"Beran": 11,
		"Beranek": 3,
		"Bercik": 1,
		"Berger": 1,
		"Berka": 2,
		"Bermann": 1,
		"Bernad": 2,
		"Bernard": 2,
		"Bernat": 1,
		"Bernovsky": 1,
		"Beroun": 2,
		"Beránek": 3,
		"Bezdek": 1,
		"Bezouska": 1,
		"Bezpalec": 1,
		"Bezstarosti": 1,
		"Bialy": 1,
		"Bibr": 1,
		"Bican": 1,
		"Bicha": 1,
		"Bilcík": 1,
		"Bilek": 6,
		"Binias": 1,
		"Binko": 2,
		"Birner": 1,
		"Bitman": 1,
		"Bitomsky": 1,
		"Bittner": 1,
		"Bizon": 1,
		"Blaha": 8,
		"Blahout": 1,
		"Blanarova": 1,
		"Blanár": 1,
		"Blasko": 1,
		"Blazej": 1,
		"Blazek": 8,
		"Blengino": 2,
		"Blumentrit": 1,
		"Bláha": 3,
		"Blümel": 1,
		"Bobok": 1,
		"Bochnak": 1,
		"Bodis": 1,
		"Bogac": 1,
		"Bohac": 1,
		"Bohaty": 1,
		"Bojdová": 1,
		"Bojer": 1,
		"Bokros": 1,
		"Bolehovský": 1,
		"Bolek": 2,
		"Boltvan": 1,
		"Bombic": 1,
		"Boolkah": 1,
		"Borak": 1,
		"Borkovec": 1,
		"Borodenko": 1,
		"Bortoli": 1,
		"Boruta": 1,
		"Bosacky": 1,
		"Bosek": 1,
		"Boskovic": 1,
		"Botka": 1,
		"Boukal": 1,
		"Bouril": 1,
		"Bouska": 1,
		"Bozseník": 1,
		"Brabec": 1,
		"Brabenec": 2,
		"Brada": 1,
		"Bradacek": 1,
		"Brancik": 1,
		"Branis": 1,
		"Brazdil": 1,
		"Brebera": 1,
		"Breczko": 1,
		"Brezak": 1,
		"Brezina": 2,
		"Brezovjak": 1,
		"Briska": 1,
		"Brizgala": 1,
		"Brodecky": 1,
		"Brodecký": 1,
		"Brodek": 1,
		"Brokes": 1,
		"Bros": 2,
		"Brotanek": 1,
		"Broz": 6,
		"Broza": 1,
		"Brozek": 2,
		"Brtnik": 1,
		"Brucek": 1,
		"Bruk": 1,
		"Bruna": 1,
		"Brustmann": 1,
		"Brychta": 1,
		"Brym": 1,
		"Brzek": 1,
		"Brzobohatý": 1,
		"Brzák": 1,
		"Brázdil": 2,
		"Buberl": 1,
		"Bubníková": 1,
		"Buchal": 1,
		"Buchta": 1,
		"Buchtele": 1,
		"Buda": 1,
		"Budik": 2,
		"Budina": 1,
		"Budínský": 1,
		"Bukac": 1,
		"Bulat": 1,
		"Bulik": 1,
		"Bulir": 1,
		"Bulka": 1,
		"Burda": 3,
		"Bures": 2,
		"Burger": 2,
		"Burget": 1,
		"Burian": 2,
		"Buric": 1,
		"Burjánek": 1,
		"Bursik": 2,
		"Buscík": 1,
		"Busta": 1,
		"Buzek": 2,
		"Byakov": 1,
		"Bydzovsky": 1,
		"Byrtus": 1,
		"Bystricky": 1,
		"Bystron": 3,
		"Bárta": 1,
		"Bätge": 1,
		"Bílek": 2,
		"Bína": 1,
		"Böhm": 1,
		"Bütikofer": 1,
		"Cach": 1,
		"Cachnin": 1,
		"Cachotský": 1,
		"Cada": 2,
		"Cais": 1,
		"Cajan": 1,
		"Cajka": 1,
		"Cakajik": 1,
		"Cakl": 1,
		"Caloun": 3,
		"Camek": 1,
		"Cancik": 1,
		"Cancura": 1,
		"Cano": 1,
		"Cap": 1,
		"Capil": 1,
		"Carda": 2,
		"Carvan": 1,
		"Cecetka": 2,
		"Cech": 11,
		"Cechmanek": 1,
		"Cejka": 2,
		"Cejpek": 1,
		"Cejtchaml": 1,
		"Cermak": 15,
		"Cerman": 1,
		"Cermák": 2,
		"Cernik": 1,
		"Cernoch": 1,
		"Cernohorský": 1,
		"Cernohous": 1,
		"Cerny": 11,
		"Cerný": 1,
		"Cervenka": 4,
		"Cerveny": 3,
		"Cervený": 1,
		"Cervicek": 1,
		"Cervinka": 1,
		"Ceslar": 1,
		"Cesnohlídek": 1,
		"Cestr": 2,
		"Chab": 1,
		"Chabada": 1,
		"Chaloupka": 5,
		"Chalupa": 5,
		"Chamrad": 1,
		"Charvat": 2,
		"Charvát": 4,
		"Chasák": 1,
		"Chladek": 1,
		"Chlan": 1,
		"Chlapík": 3,
		"Chlubna": 4,
		"Chludil": 3,
		"Chládek": 1,
		"Chlán": 1,
		"Chmel": 3,
		"Chmelar": 1,
		"Chmelik": 1,
		"Chmiel": 1,
		"Chocholousek": 1,
		"Choma": 1,
		"Chomic": 1,
		"Choutka": 1,
		"Chovanec": 2,
		"Chrenka": 1,
		"Christov": 1,
		"Chrobocek": 1,
		"Chromy": 1,
		"Chrtek": 1,
		"Churacek": 1,
		"Chvatal": 1,
		"Chvátal": 2,
		"Chylik": 1,
		"Chylík": 1,
		"Chymo": 1,
		"Chytil": 1,
		"Chára": 1,
		"Cibulka": 1,
		"Cibuzar": 1,
		"Cicha": 1,
		"Cichon": 2,
		"Cienciala": 1,
		"Cifka": 1,
		"Cihak": 1,
		"Cihal": 1,
		"Cihar": 1,
		"Cihlar": 1,
		"Cimrman": 1,
		"Cincala": 1,
		"Cinka": 1,
		"Ciolek": 1,
		"Cip": 1,
		"Cipko": 1,
		"Cisar": 1,
		"Cisarik": 1,
		"Civis": 1,
		"Cizek": 4,
		"Cmiel": 2,
		"Compel": 1,
		"Coufal": 2,
		"Coupek": 1,
		"Crosby": 1,
		"Csabi": 1,
		"Csamango": 1,
		"Cuba": 1,
		"Cubo": 1,
		"Culek": 1,
		"Cunat": 1,
		"Curran": 1,
		"Curík": 1,
		"Cutta": 1,
		"Cuzna": 1,
		"Cvek": 1,
		"Cvikl": 1,
		"Czudek": 1,
		"Czyz": 1,
		"Cáp": 3,
		"Cáslava": 1,
		"Cízek": 1,
		"Dalecký": 1,
		"Damasek": 2,
		"Dana": 2,
		"Dancisin": 1,
		"Danecek": 1,
		"Danecko": 1,
		"Danek": 3,
		"Dang": 1,
		"Danicek": 1,
		"Daniel": 1,
		"Danihelka": 1,
		"Daron": 1,
		"Darsova": 1,
		"Dautovsky": 1,
		"David": 3,
		"Davídek": 2,
		"Dedek": 2,
		"Dej": 1,
		"Demel": 6,
		"Demitra": 1,
		"Derka": 1,
		"Deutsch": 1,
		"Dibelka": 1,
		"Dietrich": 1,
		"Dietz": 1,
		"Dittrich": 1,
		"Divis": 3,
		"Divisek": 1,
		"Dlapa": 1,
		"Dlouhý": 5,
		"Dluhos": 1,
		"Dobes": 2,
		"Dobias": 1,
		"Dobner": 1,
		"Dobos": 1,
		"Dobrecky": 1,
		"Dobremysl": 2,
		"Dobsa": 2,
		"Docekal": 4,
		"Dockal": 2,
		"Dohnal": 4,
		"Doktor": 1,
		"Dolak": 1,
		"Dolana": 1,
		"Dolejs": 1,
		"Dolezal": 7,
		"Dolezel": 1,
		"Dolhy": 1,
		"Doliska": 1,
		"Dolnicek": 2,
		"Domansky": 1,
		"Domkar": 1,
		"Dornic": 1,
		"Dorot": 1,
		"Dosek": 1,
		"Doskocil": 1,
		"Doslik": 1,
		"Dospel": 1,
		"Dostal": 3,
		"Dostalek": 1,
		"Dotter": 1,
		"Douda": 2,
		"Doudera": 5,
		"Dousa": 1,
		"Drab": 1,
		"Drabcik": 1,
		"Drabek": 3,
		"Dragon": 1,
		"Dragoun": 1,
		"Draisaitl": 2,
		"Drancak": 1,
		"Drastil": 1,
		"Dravecký": 1,
		"Dresler": 1,
		"Drlik": 1,
		"Drobisz": 1,
		"Drtil": 1,
		"Drtina": 2,
		"Drábek": 1,
		"Duba": 1,
		"Dubec": 1,
		"Duben": 2,
		"Dubrava": 1,
		"Dubský": 1,
		"Duchacek": 2,
		"Duchan": 1,
		"Duda": 4,
		"Dudacek": 1,
		"Dudek": 1,
		"Dudycha": 1,
		"Dufek": 7,
		"Dujsik": 1,
		"Dulovec": 1,
		"Dunda": 1,
		"Dundácek": 1,
		"Durkac": 1,
		"Durkech": 1,
		"Dusek": 10,
		"Dvoracek": 2,
		"Dvorak": 12,
		"Dvorák": 15,
		"Dybal": 3,
		"Dycka": 1,
		"Dyk": 1,
		"Dymak": 1,
		"Döring": 2,
		"Ebenstreit": 1,
		"Eberle": 1,
		"Eder": 1,
		"Egart": 1,
		"Ehrenberg": 1,
		"Ehrenberger": 3,
		"Eich": 1,
		"Eichler": 1,
		"Eiselt": 1,
		"Eismann": 1,
		"Ekrt": 2,
		"Elias": 2,
		"Elis": 1,
		"Eminger": 1,
		"Endál": 1,
		"Erat": 1,
		"Eremias": 2,
		"Eret": 1,
		"Esender": 1,
		"Exner": 1,
		"Fabera": 1,
		"Fabry": 1,
		"Fadrný": 1,
		"Fagos": 1,
		"Faigl": 1,
		"Fajgl": 1,
		"Fajkus": 1,
		"Fajmon": 1,
		"Faksa": 1,
		"Falhar": 1,
		"Falta": 2,
		"Falter": 1,
		"Faltys": 1,
		"Faschingbauer": 1,
		"Fasner": 4,
		"Feco": 2,
		"Fedor": 1,
		"Feher": 1,
		"Fejko": 1,
		"Fejt": 1,
		"Felcman": 1,
		"Ferda": 1,
		"Ferdus": 1,
		"Ferenc": 1,
		"Fetter": 1,
		"Fiala": 10,
		"Fibigr": 2,
		"Ficek": 1,
		"Ficenec": 2,
		"Filip": 4,
		"Filipek": 1,
		"Filippi": 1,
		"Fink": 1,
		"Finsterle": 1,
		"Fischer": 6,
		"Fiser": 2,
		"Fisera": 1,
		"Flaksa": 1,
		"Fleischman": 1,
		"Flek": 1,
		"Flok": 1,
		"Florian": 4,
		"Floryk": 1,
		"Flynn": 1,
		"Fodor": 1,
		"Foerster": 1,
		"Fojt": 2,
		"Fojtik": 7,
		"Fojtík": 1,
		"Folda": 1,
		"Foltyn": 1,
		"Foltýn": 1,
		"Forejtek": 1,
		"Forman": 2,
		"Formanek": 2,
		"Forst": 1,
		"Fort": 1,
		"Fosum": 1,
		"Fousek": 1,
		"Francouz": 1,
		"Franek": 1,
		"Frano": 2,
		"Frantl": 1,
		"Frejka": 1,
		"Frgal": 1,
		"Fridrich": 1,
		"Frk": 1,
		"Frnka": 1,
		"Frodl": 1,
		"Frolik": 1,
		"Frolo": 1,
		"Frolík": 3,
		"From": 1,
		"Fromm-Delorme": 1,
		"Fronk": 1,
		"Fryc": 1,
		"Fryda": 1,
		"Frydek": 1,
		"Frömel": 2,
		"Fucik": 1,
		"Funk": 1,
		"Furch": 4,
		"Furda": 1,
		"Fuzik": 1,
		"Fábera": 1,
		"Fábry": 1,
		"Fürst": 1,
		"Gabriska": 1,
		"Gago": 1,
		"Gajarský": 1,
		"Gajda": 1,
		"Gajdolin": 1,
		"Gajovský": 1,
		"Galansky": 1,
		"Galnor": 1,
		"Galvas": 2,
		"Gardon": 1,
		"Gaspar": 4,
		"Gazda": 1,
		"Gebauer": 2,
		"Geidl": 2,
		"Gelhof": 1,
		"Gengel": 1,
		"Gerstner": 1,
		"Gerych": 1,
		"Gerza": 1,
		"Gewiese": 1,
		"Giesl": 1,
		"Gistr": 1,
		"Glas": 1,
		"Glos": 3,
		"Goga": 1,
		"Gogolka": 1,
		"Gois": 1,
		"Gola": 2,
		"Gorcik": 1,
		"Gottfried": 1,
		"Grabowski": 1,
		"Grametbauer": 1,
		"Granecny": 1,
		"Grauer": 2,
		"Grebenicek": 1,
		"Gregar": 1,
		"Gregorek": 1,
		"Gres": 1,
		"Gresik": 1,
		"Grof": 1,
		"Groh": 1,
		"Gross": 3,
		"Grosskopf": 1,
		"Gryc": 1,
		"Grygar": 1,
		"Grzymek": 1,
		"Gudas": 2,
		"Guggenheim": 1,
		"Gula": 3,
		"Gulasi": 1,
		"Gulda": 4,
		"Guman": 1,
		"Guryca": 1,
		"Guryevskiy": 1,
		"Gustu": 1,
		"Gut": 1,
		"Gutwald": 1,
		"Gába": 1,
		"Haas": 4,
		"Habal": 1,
		"Habermann": 1,
		"Hadrava": 1,
		"Hafenrichter": 1,
		"Hajda": 1,
		"Hajek": 6,
		"Hajic": 1,
		"Haken": 1,
		"Hala": 1,
		"Halacka": 1,
		"Haloda": 4,
		"Haltuf": 1,
		"Hamak": 1,
		"Hamalcik": 1,
		"Haman": 4,
		"Hamara": 2,
		"Hambalek": 1,
		"Hammerbauer": 1,
		"Hampl": 6,
		"Hamr": 2,
		"Hamrik": 1,
		"Hamrla": 3,
		"Hamrlík": 1,
		"Hamrsmid": 1,
		"Hanak": 3,
		"Hanauer": 1,
		"Handl": 3,
		"Hanousek": 8,
		"Hansel": 1,
		"Hanson": 1,
		"Hanuljak": 1,
		"Hanus": 2,
		"Hanys": 1,
		"Hanzak": 1,
		"Hanzal": 1,
		"Hanzl": 2,
		"Hanzlik": 1,
		"Hanzlík": 1,
		"Hanák": 1,
		"Harasek": 1,
		"Harkabus": 3,
		"Harmim": 1,
		"Hartl": 1,
		"Has": 1,
		"Hasek": 3,
		"Haslar": 1,
		"Hasman": 2,
		"Haspeklo": 1,
		"Hauptvogel": 1,
		"Hauser": 1,
		"Hausner": 1,
		"Hava": 1,
		"Havel": 6,
		"Havelka": 2,
		"Havir": 1,
		"Havlas": 1,
		"Havlicek": 3,
		"Havlik": 6,
		"Havlin": 2,
		"Havluj": 2,
		"Havlát": 1,
		"Havlícek": 1,
		"Havlík": 4,
		"Havranek": 1,
		"Havrda": 1,
		"Havránek": 5,
		"Hayek": 1,
		"Haz": 1,
		"Hebar": 1,
		"Hebek": 2,
		"Hecko": 2,
		"Heczko": 1,
		"Hefka": 1,
		"Heider": 2,
		"Heinisch": 1,
		"Heinrich": 1,
		"Heinzl": 1,
		"Hejcman": 1,
		"Hejda": 1,
		"Hejduk": 2,
		"Hejnak": 1,
		"Heligr": 1,
		"Helikar": 1,
		"Helis": 1,
		"Heller": 1,
		"Helt": 1,
		"Hemský": 1,
		"Hendrych": 2,
		"Hercik": 2,
		"Herkommer": 1,
		"Herm": 1,
		"Herman": 4,
		"Hermann": 1,
		"Herr": 1,
		"Hertl": 1,
		"Herynk": 1,
		"Herzan": 1,
		"Herzig": 1,
		"Hes": 2,
		"Hess": 1,
		"Hilser": 2,
		"Hinner": 1,
		"Hladik": 2,
		"Hladil": 1,
		"Hladonik": 2,
		"Hladík": 1,
		"Hlava": 1,
		"Hlavac": 3,
		"Hlavacek": 1,
		"Hlavaty": 1,
		"Hlavatý": 1,
		"Hlavicka": 1,
		"Hlavka": 2,
		"Hlavác": 1,
		"Hlavácek": 1,
		"Hlineny": 1,
		"Hlinka": 8,
		"Hlinský": 1,
		"Hlousek": 1,
		"Hlozanek": 1,
		"Hlozek": 2,
		"Hnat": 1,
		"Hnik": 1,
		"Hnilicka": 1,
		"Hobza": 1,
		"Hoch": 1,
		"Hodak": 1,
		"Hodinar": 1,
		"Hodný": 1,
		"Hofman": 3,
		"Hofmann": 1,
		"Hofrajtr": 1,
		"Hohl": 2,
		"Hois": 1,
		"Holak": 1,
		"Holan": 5,
		"Holas": 1,
		"Holba": 2,
		"Holcak": 1,
		"Holec": 1,
		"Holecek": 2,
		"Holejsovsky": 4,
		"Holemý": 1,
		"Holenda": 1,
		"Holes": 1,
		"Holik": 1,
		"Holinka": 1,
		"Holis": 1,
		"Hollar": 1,
		"Holoubek": 1,
		"Holous": 1,
		"Holub": 5,
		"Holubar": 1,
		"Holubec": 1,
		"Holík": 1,
		"Holý": 1,
		"Homola": 3,
		"Honejsek": 1,
		"Honisch": 1,
		"Honzik": 2,
		"Hora": 5,
		"Horacek": 3,
		"Horak": 4,
		"Horansky": 1,
		"Horava": 2,
		"Horcicka": 1,
		"Horejsi": 2,
		"Horinek": 1,
		"Horkel": 1,
		"Horky": 2,
		"Horký": 1,
		"Horna": 1,
		"Hornicek": 1,
		"Hornych": 1,
		"Horsky": 2,
		"Horyl": 2,
		"Horyna": 1,
		"Horák": 5,
		"Hosnedl": 1,
		"Hospodka": 1,
		"Hotek": 1,
		"Houdek": 3,
		"Houfek": 1,
		"Houska": 1,
		"Hovorka": 2,
		"Hozak": 1,
		"Hoznourek": 1,
		"Hrabal": 2,
		"Hrabcak": 2,
		"Hrabik": 2,
		"Hrabinec": 1,
		"Hrachovina": 3,
		"Hrachovsky": 1,
		"Hradec": 1,
		"Hradecký": 1,
		"Hradil": 3,
		"Hradil Dzudza": 1,
		"Hrala": 1,
		"Hrasek": 1,
		"Hrazdira": 1,
		"Hrbas": 1,
		"Hrbek": 1,
		"Hrcek": 2,
		"Hrdel": 1,
		"Hrdina": 1,
		"Hrdinka": 1,
		"Hrdlicka": 5,
		"Hrdy": 1,
		"Hrebejk": 1,
		"Hrebicek": 2,
		"Hric": 1,
		"Hrna": 1,
		"Hrncir": 1,
		"Hrnicko": 1,
		"Hrodek": 1,
		"Hromada": 1,
		"Hromadka": 1,
		"Hron": 3,
		"Hronek": 1,
		"Hrouda": 3,
		"Hrubec": 2,
		"Hruby": 7,
		"Hruska": 12,
		"Hruzek": 1,
		"Hryciow": 1,
		"Hrádek": 1,
		"Hríbal": 1,
		"Hub": 1,
		"Hubacek": 3,
		"Hubata": 1,
		"Hubik": 1,
		"Hubinka": 1,
		"Hubnik": 3,
		"Hucko": 1,
		"Hudecek": 2,
		"Hudácek": 1,
		"Huf": 1,
		"Huja": 1,
		"Hujer": 1,
		"Huk": 1,
		"Hulcr": 1,
		"Humenik": 1,
		"Hunady": 1,
		"Hurný": 1,
		"Hurt": 1,
		"Hurta": 1,
		"Husa": 1,
		"Husarik": 1,
		"Husek": 1,
		"Husinecký": 1,
		"Hybner": 1,
		"Hyka": 1,
		"Hykl": 1,
		"Hynek": 6,
		"Hájek": 2,
		"Hák": 1,
		"Hása": 1,
		"Häring": 2,
		"Höhlig": 1,
		"Höll": 1,
		"Hübl": 2,
		"Hüttl": 1,
		"Ibrisek": 1,
		"Illés": 1,
		"Indrak": 1,
		"Indrst": 2,
		"Irgl": 1,
		"Iterský": 1,
		"Ivan": 5,
		"Izacky": 1,
		"Izak": 1,
		"Jablonsky": 1,
		"Jachym": 2,
		"Jackuliak": 1,
		"Jaglar": 1,
		"Jagr": 1,
		"Jahn": 1,
		"Jakab": 1,
		"Jakub": 1,
		"Jakubec": 4,
		"Janak": 1,
		"Janata": 1,
		"Janca": 1,
		"Jancarik": 1,
		"Janda": 2,
		"Jandac": 1,
		"Jandus": 2,
		"Janeba": 1,
		"Janecek": 7,
		"Janech": 1,
		"Janek": 1,
		"Jank": 1,
		"Jankovský": 1,
		"Janoch": 1,
		"Janota": 1,
		"Janousek": 3,
		"Jansa": 4,
		"Jansky": 2,
		"Januszewski": 1,
		"Jarabko": 1,
		"Jarabková": 1,
		"Jarmara": 1,
		"Jarolim": 7,
		"Jarolím": 1,
		"Jaros": 5,
		"Jarusek": 1,
		"Jasa": 1,
		"Jasecko": 1,
		"Jasek": 1,
		"Jaskin": 1,
		"Javorek": 1,
		"Javurek": 1,
		"Jebavý": 1,
		"Jech": 1,
		"Jecho": 1,
		"Jedlicka": 2,
		"Jekel": 1,
		"Jeletz": 1,
		"Jelinek": 6,
		"Jelínek": 3,
		"Jenacek": 1,
		"Jencovsky": 1,
		"Jenka": 2,
		"Jenys": 1,
		"Jenácek": 2,
		"Jeník": 1,
		"Jerabek": 5,
		"Jergl": 2,
		"Jerman": 1,
		"Jeschke": 1,
		"Jessl": 1,
		"Jezek": 6,
		"Jindra": 1,
		"Jiranek": 1,
		"Jiratko": 1,
		"Jirgle": 1,
		"Jiricek": 2,
		"Jirik": 1,
		"Jirku": 2,
		"Jirota": 1,
		"Jirousek": 1,
		"Jirout": 2,
		"Jirovec": 1,
		"Jirus": 1,
		"Jiskra": 1,
		"Jobanek": 1,
		"Jokl": 1,
		"Jon": 1,
		"Jonak": 4,
		"Jonák": 1,
		"Jordan": 1,
		"Jordán": 1,
		"Josefus": 1,
		"Joska": 1,
		"Jouza": 1,
		"Juda": 3,
		"Jugová": 1,
		"Juhász": 1,
		"Jun": 1,
		"Junek": 1,
		"Jung": 2,
		"Jungwirth": 3,
		"Juran": 2,
		"Jurasek": 1,
		"Jurca": 1,
		"Jurcik": 1,
		"Jurek": 1,
		"Juricek": 1,
		"Jurik": 1,
		"Jurny": 2,
		"Jursa": 1,
		"Jurík": 1,
		"Justa": 1,
		"Jáchym": 1,
		"Jágr": 1,
		"Jäger": 1,
		"Jícha": 2,
		"Kabelka": 1,
		"Kacbunda": 1,
		"Kacetl": 1,
		"Kachlir": 1,
		"Kachyna": 1,
		"Kacirek": 1,
		"Kadera": 1,
		"Kaderavek": 1,
		"Kadlc": 1,
		"Kadlcik": 1,
		"Kadlec": 7,
		"Kadlecek": 1,
		"Kadula": 1,
		"Kafka": 3,
		"Kahanek": 1,
		"Kahoun": 1,
		"Kahun": 1,
		"Kaiser": 2,
		"Kalac": 2,
		"Kalandra": 1,
		"Kalcik": 2,
		"Kaleta": 1,
		"Kalina": 6,
		"Kalinin": 1,
		"Kalis": 1,
		"Kalista": 2,
		"Kalivoda": 3,
		"Kalkus": 1,
		"Kalla": 1,
		"Kalny": 1,
		"Kalous": 1,
		"Kalousek": 1,
		"Kaltenböck": 1,
		"Kalus": 6,
		"Kaluzik": 2,
		"Kalvoda": 1,
		"Kamas": 1,
		"Kamenicek": 1,
		"Kamenicky": 1,
		"Kamenik": 1,
		"Kames": 3,
		"Kana": 2,
		"Kanak": 1,
		"Kandrak": 1,
		"Kania": 2,
		"Kanis": 1,
		"Kanka": 2,
		"Kanko": 1,
		"Kankovsky": 3,
		"Kankovský": 2,
		"Kantner": 1,
		"Kantor": 1,
		"Kanák": 1,
		"Kapicka": 1,
		"Kaplan": 1,
		"Kapoun": 2,
		"Karabacek": 1,
		"Karafiat": 1,
		"Karal": 1,
		"Karas": 2,
		"Karbulka": 2,
		"Karásek": 1,
		"Kasal": 1,
		"Kasalý": 1,
		"Kase": 2,
		"Kasik": 1,
		"Kaspar": 7,
		"Kasperlík": 2,
		"Kastanek": 2,
		"Kastner": 1,
		"Kaszper": 1,
		"Kasík": 2,
		"Katolicky": 1,
		"Katzer": 1,
		"Kaufman": 1,
		"Kaukic": 1,
		"Kaut": 2,
		"Kavan": 1,
		"Keller": 2,
		"Kelnar": 1,
		"Keltner": 1,
		"Kempný": 1,
		"Kerber": 1,
		"Kerbler": 1,
		"Kerekanic": 1,
		"Kern": 1,
		"Keszi": 1,
		"Kharboutli": 2,
		"Khokhlov": 1,
		"Kiedron": 1,
		"Kijonka": 1,
		"Kincl": 1,
		"Kindl": 7,
		"Kinter": 1,
		"Kirschbaum": 1,
		"Kisliuk": 1,
		"Kisza": 1,
		"Kivader": 1,
		"Kjellin": 2,
		"Kladivo": 1,
		"Klanica": 1,
		"Klapka": 1,
		"Klasna": 1,
		"Klatovsky": 1,
		"Klaus": 1,
		"Klecacky": 1,
		"Klecka": 1,
		"Klejna": 1,
		"Klement": 1,
		"Klempir": 1,
		"Klepis": 1,
		"Kleveta": 1,
		"Klhufek": 1,
		"Klicka": 1,
		"Klika": 1,
		"Klikorka": 1,
		"Klima": 8,
		"Klimek": 4,
		"Kliment": 1,
		"Klimes": 5,
		"Klimicek": 1,
		"Klimsa": 2,
		"Klinecký": 1,
		"Klinger": 1,
		"Klir": 1,
		"Kloboucek": 1,
		"Klodner": 1,
		"Klok": 1,
		"Klos": 1,
		"Kloucek": 1,
		"Klouda": 1,
		"Kloutvor": 1,
		"Kloz": 3,
		"Klust": 1,
		"Klíma": 2,
		"Kmec": 1,
		"Kment": 1,
		"Kmonicek": 1,
		"Knakal": 2,
		"Knesl": 1,
		"Knot": 1,
		"Knotek": 2,
		"Koblasa": 1,
		"Koblizek": 2,
		"Kocara": 1,
		"Kocek": 1,
		"Kochanek": 1,
		"Koci": 5,
		"Kocica": 2,
		"Kocourek": 1,
		"Kocyan": 1,
		"Kodýtek": 1,
		"Koffer": 1,
		"Kofron": 3,
		"Kohler": 1,
		"Kohlicek": 1,
		"Kohout": 2,
		"Kohutek": 1,
		"Kokes": 1,
		"Kokoska": 1,
		"Koky": 1,
		"Kolacek": 2,
		"Kolar": 8,
		"Kolarik": 3,
		"Kolarík": 3,
		"Kolat": 1,
		"Kolbl": 1,
		"Kolda": 1,
		"Kolek": 1,
		"Kollar": 2,
		"Kollmann": 1,
		"Kolmann": 1,
		"Kolner": 1,
		"Kolouch": 1,
		"Komanec": 1,
		"Kominek": 1,
		"Komma": 1,
		"Konasek": 1,
		"Koncicky": 1,
		"Kondelik": 1,
		"Konecny": 6,
		"Konir": 1,
		"Konvalina": 1,
		"Konvalinka": 1,
		"Kopecky": 4,
		"Kopecký": 2,
		"Kopic": 7,
		"Kopriva": 1,
		"Kopta": 1,
		"Koran": 1,
		"Koranek": 1,
		"Korbel": 1,
		"Korcak": 1,
		"Korcian": 1,
		"Kordule": 1,
		"Korec": 3,
		"Korecký": 1,
		"Korenar": 1,
		"Korenek": 2,
		"Korhon": 1,
		"Korinek": 1,
		"Korytar": 1,
		"Kos": 5,
		"Kosar": 1,
		"Kosik": 1,
		"Kosnar": 2,
		"Kostal": 5,
		"Kostalek": 1,
		"Kostka": 1,
		"Kostourek": 1,
		"Kostoval": 1,
		"Kota": 1,
		"Kotala": 2,
		"Kotas": 1,
		"Kotasek": 2,
		"Kotek": 1,
		"Koten": 1,
		"Kotlas": 1,
		"Kotous": 1,
		"Kotrba": 1,
		"Kotrla": 1,
		"Kotyza": 1,
		"Kotásek": 1,
		"Koubek": 2,
		"Koudela": 2,
		"Koudelka": 2,
		"Koudelny": 1,
		"Koukal": 4,
		"Koupal": 1,
		"Kousal": 4,
		"Koutecky": 1,
		"Kovac": 1,
		"Koval": 1,
		"Kovalcik": 1,
		"Kovanda": 1,
		"Kovar": 7,
		"Kovarcik": 2,
		"Kovarik": 2,
		"Kovár": 3,
		"Kowalczyk": 2,
		"Kozak": 4,
		"Kozik": 1,
		"Kozlik": 3,
		"Kozubik": 1,
		"Krajcik": 1,
		"Krajdl": 1,
		"Krajícek": 2,
		"Kral": 9,
		"Kralicek": 1,
		"Krasa": 1,
		"Krasanovsky": 2,
		"Kratky": 2,
		"Kratochvil": 6,
		"Kratochvíl": 1,
		"Kratoska": 1,
		"Kraucuk": 1,
		"Kraus": 2,
		"Kravec": 1,
		"Krbecek": 2,
		"Krcal": 1,
		"Krchnak": 1,
		"Krcho": 1,
		"Krecan": 1,
		"Krecek": 1,
		"Kredl": 1,
		"Krehlik": 1,
		"Krej í": 1,
		"Krejca": 1,
		"Krejci": 5,
		"Krejcik": 2,
		"Krejcirik": 1,
		"Krejcí": 3,
		"Krejcík": 4,
		"Krejsa": 2,
		"Krejza": 1,
		"Krelina": 1,
		"Kremen": 2,
		"Kremlacek": 1,
		"Krenek": 1,
		"Krenzelok": 2,
		"Krepel": 1,
		"Krepelka": 1,
		"Krestan": 2,
		"Kretschmer": 1,
		"Krisko": 1,
		"Krisl": 1,
		"Kristan": 1,
		"Kristek": 1,
		"Krivanek": 1,
		"Krivohlavek": 1,
		"Kriz": 7,
		"Krizek": 1,
		"Krizenecky": 1,
		"Krlis": 1,
		"Krofta": 1,
		"Kron": 1,
		"Kropác": 1,
		"Kroupa": 2,
		"Krpalek": 1,
		"Krpata": 1,
		"Krpenský": 1,
		"Krsek": 1,
		"Krsik": 1,
		"Krstev": 1,
		"Krupicka": 1,
		"Krupka": 2,
		"Krutil": 2,
		"Krutina": 1,
		"Krutis": 1,
		"Kruzik": 1,
		"Krzak": 1,
		"Král": 4,
		"Krämer": 1,
		"Kríz": 1,
		"Krögler": 1,
		"Kuba": 2,
		"Kubalik": 2,
		"Kuban": 1,
		"Kubanek": 1,
		"Kubani": 1,
		"Kubat": 1,
		"Kubatik": 1,
		"Kubecka": 2,
		"Kubes": 2,
		"Kubica": 4,
		"Kubicek": 6,
		"Kubiesa": 1,
		"Kubik": 4,
		"Kubin": 1,
		"Kubis": 1,
		"Kubista": 3,
		"Kubos": 1,
		"Kubát": 1,
		"Kubík": 1,
		"Kucera": 18,
		"Kucerik": 1,
		"Kucernak": 1,
		"Kucharcik": 2,
		"Kucharczyk": 1,
		"Kucharik": 2,
		"Kuchler": 1,
		"Kuchta": 4,
		"Kuchynka": 1,
		"Kucny": 1,
		"Kucsera": 1,
		"Kudelka": 3,
		"Kudrna": 2,
		"Kufa": 1,
		"Kukene": 1,
		"Kukla": 1,
		"Kukleta": 1,
		"Kuklík": 1,
		"Kulhanek": 1,
		"Kulich": 3,
		"Kulinic": 1,
		"Kulvejt": 1,
		"Kunc": 3,
		"Kuncek": 1,
		"Kundrátek": 1,
		"Kunst": 1,
		"Kunstler": 1,
		"Kunstmüller": 1,
		"Kupco": 1,
		"Kurajský": 1,
		"Kurecka": 1,
		"Kurfürst": 1,
		"Kurial": 1,
		"Kurka": 4,
		"Kurnat": 1,
		"Kurovsky": 1,
		"Kurz": 1,
		"Kusak": 1,
		"Kusta": 2,
		"Kusy": 2,
		"Kusý": 1,
		"Kut": 1,
		"Kutak": 1,
		"Kutlvasr": 1,
		"Kuzilek": 1,
		"Kuzin": 1,
		"Kuzma": 1,
		"Kvaca": 1,
		"Kvas": 2,
		"Kvasnica": 1,
		"Kvasnicka": 4,
		"Kverka": 7,
		"Kveton": 1,
		"Kyjanka": 1,
		"Kyjovsky": 1,
		"Kylnar": 1,
		"Kyncl": 4,
		"Kysela": 5,
		"Kysilka": 1,
		"Kytka": 1,
		"Kyznar": 1,
		"Kácha": 1,
		"Kána": 5,
		"Kämpf": 1,
		"Köhler": 1,
		"Labuzik": 2,
		"Laca": 1,
		"Laciga": 1,
		"Lacnak": 1,
		"Ladra": 1,
		"Lakatos": 1,
		"Lakomy": 1,
		"Lakosil": 1,
		"Landa": 1,
		"Landsman": 1,
		"Lang": 5,
		"Langer": 2,
		"Langhamer": 1,
		"Langmeier": 1,
		"Lapes": 1,
		"Larys": 1,
		"Lasak": 1,
		"Laskavyj": 1,
		"Latal": 1,
		"Lattner": 1,
		"Lauko": 1,
		"Lavinger": 1,
		"Lazar": 1,
		"Leden": 1,
		"Leder": 1,
		"Ledl": 1,
		"Lednicky": 1,
		"Lehecka": 1,
		"Leinweber": 1,
		"Lekes": 1,
		"Lempach": 1,
		"Lenc": 1,
		"Lengö": 1,
		"Lepik": 1,
		"Lequin": 1,
		"Lerch": 1,
		"Leska": 1,
		"Lesko": 1,
		"Lev": 2,
		"Levai": 1,
		"Lexa": 1,
		"Lhotak": 1,
		"Lichtag": 1,
		"Licka": 2,
		"Liemann": 1,
		"Lilge": 1,
		"Linet": 2,
		"Lingr": 1,
		"Lipka": 1,
		"Liptaj": 1,
		"Lisler": 1,
		"Liss": 1,
		"Lobo": 1,
		"Lojek": 1,
		"Lokajicek": 2,
		"Lomicky": 1,
		"Lomoz": 1,
		"Lorenz": 1,
		"Loschner": 1,
		"Loukota": 1,
		"Loza": 1,
		"Lucan": 1,
		"Ludvig": 2,
		"Ludvik": 3,
		"Ludvík": 1,
		"Luka": 1,
		"Lukas": 4,
		"Lukastik": 1,
		"Lukea": 1,
		"Lukes": 4,
		"Lunak": 1,
		"Lunák": 4,
		"Luska": 1,
		"Lustinec": 1,
		"Luza": 1,
		"Lycka": 1,
		"Lysonek": 1,
		"Lytvynov": 1,
		"Láska": 1,
		"Látal": 3,
		"Líbal": 1,
		"Löffler": 1,
		"Lönnemyr": 1,
		"Macecek": 1,
		"Macek": 3,
		"Mach": 6,
		"Macha": 2,
		"Machac": 3,
		"Machacek": 6,
		"Machala": 4,
		"Machovsky": 3,
		"Machu": 1,
		"Machyna": 1,
		"Machác": 1,
		"Machácek": 4,
		"Macias": 2,
		"Macicek": 1,
		"Mack": 1,
		"Macku": 1,
		"Macourek": 1,
		"Macura": 1,
		"Madar": 1,
		"Mahlej": 1,
		"Mahmutovic": 1,
		"Mahovský": 1,
		"Majer": 2,
		"Majkus": 1,
		"Makarius": 2,
		"Makovec": 3,
		"Mala": 1,
		"Malac": 1,
		"Malak": 1,
		"Malat": 1,
		"Malayev": 1,
		"Malek": 3,
		"Malenovsky": 1,
		"Malik": 2,
		"Malinek": 2,
		"Malinsky": 1,
		"Malinský": 1,
		"Maliník": 1,
		"Malir": 1,
		"Malis": 1,
		"Malota": 1,
		"Malovicky": 1,
		"Maly": 4,
		"Malík": 4,
		"Malý": 1,
		"Man": 2,
		"Manas": 1,
		"Manasek": 1,
		"Mandys": 2,
		"Mandát": 1,
		"Manek": 1,
		"Manik": 1,
		"Marak": 1,
		"Marcel": 2,
		"Marcilis": 1,
		"Marecek": 1,
		"Marek": 5,
		"Mares": 8,
		"Marha": 1,
		"Marik": 3,
		"Mariska": 1,
		"Marjanovic": 1,
		"Markov": 1,
		"Marossy": 1,
		"Marosz": 1,
		"Marousek": 2,
		"Marsik": 1,
		"Martinak": 1,
		"Martinec": 4,
		"Martinek": 2,
		"Martinik": 1,
		"Martinka": 1,
		"Martinková": 1,
		"Martinu": 1,
		"Marton": 1,
		"Martínek": 3,
		"Masa": 1,
		"Masar": 1,
		"Masek": 3,
		"Masin": 1,
		"Masopust": 1,
		"Mastalirsky": 1,
		"Mastera": 1,
		"Masín": 3,
		"Matai": 1,
		"Matas": 1,
		"Matasovsky": 1,
		"Matecha": 1,
		"Matej": 1,
		"Matejcek": 3,
		"Matejicek": 2,
		"Matejka": 7,
		"Matejovsky": 1,
		"Mateju": 1,
		"Matiasek": 1,
		"Matiasko": 1,
		"Matl": 2,
		"Matous": 1,
		"Matousek": 5,
		"Matula": 5,
		"Matulka": 1,
		"Matus": 1,
		"Matusík": 2,
		"Matyas": 1,
		"Matys": 1,
		"Matysek": 1,
		"Maurer": 1,
		"Maxa": 1,
		"Maxin": 1,
		"Mayer": 1,
		"Mazanec": 3,
		"Mazura": 1,
		"Mechura": 1,
		"Meciar": 1,
		"Medek": 1,
		"Medlik": 1,
		"Meidl": 3,
		"Meisel": 1,
		"Meisner": 1,
		"Mejzlik": 1,
		"Melenovský": 2,
		"Melichar": 1,
		"Melka": 1,
		"Melovsky": 1,
		"Meluzin": 2,
		"Mendlik": 1,
		"Mensator": 1,
		"Mensik": 4,
		"Menzel": 1,
		"Mert": 1,
		"Mertl": 2,
		"Mezlik": 5,
		"Mica": 1,
		"Mical": 1,
		"Mican": 1,
		"Micek": 1,
		"Michajlov": 1,
		"Michalcuk": 1,
		"Michalek": 4,
		"Michalik": 1,
		"Michalík": 1,
		"Michel": 1,
		"Michnac": 1,
		"Micka": 2,
		"Mickal": 1,
		"Miculka": 1,
		"Middleton": 1,
		"Mikel": 1,
		"Mikes": 1,
		"Mikeska": 2,
		"Miklis": 1,
		"Mikolas": 1,
		"Mikula": 9,
		"Mikulik": 1,
		"Mikulík": 2,
		"Mikyska": 3,
		"Milata": 1,
		"Milersky": 1,
		"Milfait": 1,
		"Milota": 1,
		"Minar": 2,
		"Minarik": 1,
		"Ministr": 2,
		"Misek": 1,
		"Miskar": 1,
		"Misovic": 1,
		"Mitrovic": 1,
		"Mizera": 1,
		"Mizura": 1,
		"Mlcak": 1,
		"Mlejnek": 1,
		"Mlynar": 1,
		"Mlíkovský": 1,
		"Moc": 1,
		"Mocek": 1,
		"Moder": 1,
		"Modl": 1,
		"Modry": 1,
		"Mohr": 1,
		"Mohyla": 2,
		"Mojzis": 3,
		"Mojzís": 4,
		"Mokry": 1,
		"Molek": 1,
		"Monik": 1,
		"Morava": 1,
		"Moravcik": 2,
		"Moravec": 8,
		"Morcinek": 1,
		"Moric": 1,
		"Morillas Heger": 1,
		"Morkes": 3,
		"Morkovsky": 1,
		"Morong": 1,
		"Mosnicka": 1,
		"Motak": 1,
		"Motloch": 1,
		"Motycka": 1,
		"Moucka": 1,
		"Mouka": 1,
		"Moustafa": 1,
		"Mozik": 1,
		"Mozr": 1,
		"Mracek": 1,
		"Mraz": 1,
		"Mrazek": 6,
		"Mrhalek": 1,
		"Mrkva": 1,
		"Mrna": 1,
		"Mrowiec": 1,
		"Mrtka": 2,
		"Mrva": 1,
		"Mrázek": 1,
		"Mucha": 2,
		"Mulac": 2,
		"Muron": 1,
		"Murtuzalijev": 1,
		"Musial": 1,
		"Musil": 6,
		"Muska": 1,
		"Muzatko": 1,
		"Muzik": 5,
		"Mysak": 2,
		"Mácha": 1,
		"Málek": 3,
		"Mähler": 2,
		"Míka": 1,
		"Müller": 7,
		"Münch": 1,
		"Naar": 1,
		"Nabelek": 1,
		"Nadenicek": 1,
		"Nagy": 4,
		"Nahodil": 1,
		"Najman": 3,
		"Naprstek": 1,
		"Nasel": 1,
		"Navratil": 1,
		"Navrátil": 2,
		"Nazad": 1,
		"Necas": 6,
		"Nedbal": 1,
		"Nedelka": 1,
		"Nedomlel": 1,
		"Nedorost": 1,
		"Nedrda": 1,
		"Neduchal": 1,
		"Nedved": 6,
		"Nedvidek": 1,
		"Nehasil": 1,
		"Nejcev": 1,
		"Nejedlý": 1,
		"Nekvapil": 1,
		"Nekvasil": 1,
		"Nekvinda": 1,
		"Nemec": 31,
		"Nemecek": 8,
		"Neoral": 1,
		"Nepokoj": 1,
		"Nerad": 1,
		"Nespurek": 1,
		"Nesrsta": 1,
		"Nestrasil": 2,
		"Nesvadba": 2,
		"Netik": 1,
		"Netopil": 1,
		"Netusil": 2,
		"Neuhauser": 1,
		"Neuman": 1,
		"Nevrkla": 1,
		"Nevsimal": 1,
		"Nezbeda": 1,
		"Nezmar": 1,
		"Niec": 1,
		"Niederhafner": 1,
		"Niemczyk": 1,
		"Niko": 1,
		"Norris": 1,
		"Nosek": 2,
		"Novak": 22,
		"Novosad": 1,
		"Novotny": 16,
		"Novotný": 7,
		"Novy": 1,
		"Novácek": 1,
		"Novák": 19,
		"Nowak": 1,
		"Noworyta": 1,
		"Nowák": 1,
		"Nácovský": 1,
		"Obdrzalek": 1,
		"Obermajer": 1,
		"Obrtel": 1,
		"Odehnal": 2,
		"Ohera": 2,
		"Olesz": 1,
		"Oliva": 2,
		"Oliverius": 1,
		"Olviste": 1,
		"Omelka": 1,
		"Ondracek": 2,
		"Ondracka": 1,
		"Ondrej": 1,
		"Ondrik": 1,
		"Ondrus": 1,
		"Ondrusek": 1,
		"Opravil": 2,
		"Oprchalský": 1,
		"Orct": 1,
		"Ordos": 6,
		"Orsava": 1,
		"Orsech": 1,
		"Orsulak": 1,
		"Osmera": 1,
		"Osmík": 1,
		"Ostransky": 1,
		"Ostrcil": 1,
		"Ostrizek": 1,
		"Ostry": 1,
		"Ostrízek": 1,
		"Osvald": 1,
		"Otava": 1,
		"Ourada": 1,
		"Ourednik": 1,
		"Pabiska": 1,
		"Pacan": 1,
		"Pachula": 1,
		"Pacina": 1,
		"Padelek": 1,
		"Pajer": 1,
		"Pala": 3,
		"Palan": 2,
		"Palat": 1,
		"Palecek": 1,
		"Palenik": 1,
		"Palicka": 2,
		"Panacek": 3,
		"Panec": 1,
		"Panek": 4,
		"Papez": 1,
		"Parez": 1,
		"Pargác": 1,
		"Parik": 1,
		"Parizek": 2,
		"Parshakov": 1,
		"Partl": 1,
		"Pasek": 1,
		"Pasov": 1,
		"Pastor": 2,
		"Pastrnak": 1,
		"Pastrnek": 1,
		"Patak": 1,
		"Patera": 5,
		"Patocka": 1,
		"Pavel": 1,
		"Pavelec": 2,
		"Pavelka": 9,
		"Pavic": 1,
		"Pavlacka": 1,
		"Pavlas": 2,
		"Pavlat": 1,
		"Pavlata": 1,
		"Pavlicek": 2,
		"Pavlik": 7,
		"Pavlis": 2,
		"Pavlovic": 1,
		"Pavlovsky": 1,
		"Pavlu": 1,
		"Pavlát": 1,
		"Pavlík": 7,
		"Pawliczek": 1,
		"Pazderka": 1,
		"Pazderník": 1,
		"Paze": 1,
		"Pazourek": 2,
		"Peca": 1,
		"Pecek": 1,
		"Pecen": 1,
		"Pecenka": 1,
		"Pech": 3,
		"Pechanec": 1,
		"Pechlát": 1,
		"Pecka": 1,
		"Peconka": 1,
		"Pejchal": 1,
		"Pejchar": 1,
		"Pejcharova": 1,
		"Pekar": 4,
		"Pekr": 2,
		"Peksa": 1,
		"Pelaj": 1,
		"Pelda": 1,
		"Pelici": 1,
		"Pelikan": 1,
		"Pencik": 1,
		"Pericka": 1,
		"Pernicky": 1,
		"Peroutka": 3,
		"Pertlicek": 1,
		"Pes": 2,
		"Pesak": 1,
		"Pesan": 1,
		"Peschout": 1,
		"Pesek": 3,
		"Pesl": 2,
		"Pesout": 2,
		"Pesta": 1,
		"Pestuka": 2,
		"Peterek": 2,
		"Peterka": 1,
		"Peterman": 1,
		"Petira": 1,
		"Petnik": 1,
		"Petr": 2,
		"Petrak": 1,
		"Petras": 3,
		"Petrasek": 2,
		"Petrik": 4,
		"Petrous": 2,
		"Petrs": 1,
		"Petruzalek": 1,
		"Petrzela": 2,
		"Petrzilka": 3,
		"Petrák": 1,
		"Petrásek": 1,
		"Pfeifer": 1,
		"Philipp": 1,
		"Picka": 1,
		"Picl": 1,
		"Piecha": 1,
		"Piegl": 1,
		"Pigl": 2,
		"Pilar": 4,
		"Pilch": 1,
		"Pilek": 1,
		"Pilisek": 1,
		"Pilny": 1,
		"Pinc": 1,
		"Pindel": 1,
		"Pinkas": 3,
		"Pipek": 1,
		"Pirek": 1,
		"Piroutek": 1,
		"Pisa": 1,
		"Pisarik": 1,
		"Piskacek": 1,
		"Piskor": 1,
		"Pistek": 1,
		"Pitak": 1,
		"Pitel": 1,
		"Pithart": 1,
		"Pitter": 1,
		"Pittr": 1,
		"Pitule": 1,
		"Pivonka": 1,
		"Placek": 2,
		"Plachy": 1,
		"Planava": 1,
		"Planek": 2,
		"Plasek": 1,
		"Plasil": 7,
		"Plekanec": 1,
		"Pletka": 1,
		"Pleva": 1,
		"Plicka": 1,
		"Plihal": 1,
		"Plisek": 1,
		"Plodek": 1,
		"Plos": 1,
		"Plsek": 3,
		"Pluskal": 1,
		"Plutnar": 1,
		"Pniok": 5,
		"Pocarovsky": 1,
		"Pochobradský": 1,
		"Podesva": 2,
		"Podhorsky": 1,
		"Podlaha": 1,
		"Podpera": 1,
		"Podrouzek": 1,
		"Podzimek": 1,
		"Pohanka": 1,
		"Pohl": 3,
		"Pohludka": 1,
		"Poizl": 2,
		"Pojkar": 1,
		"Pokorny": 7,
		"Pokorný": 4,
		"Polacek": 2,
		"Polach": 1,
		"Polak": 2,
		"Polame": 1,
		"Polasek": 2,
		"Polata": 2,
		"Poledna": 1,
		"Polesný": 1,
		"Poletin": 2,
		"Polka": 1,
		"Polodna": 2,
		"Polok": 1,
		"Polák": 5,
		"Polásek": 1,
		"Poncik": 1,
		"Popela": 1,
		"Popelka": 2,
		"Poppel": 1,
		"Porický": 1,
		"Porizek": 1,
		"Port": 2,
		"Pospichal": 3,
		"Pospisil": 10,
		"Pospíchal": 2,
		"Pospísil": 4,
		"Postava": 1,
		"Postl": 5,
		"Potekhin": 1,
		"Potesil": 1,
		"Potocny": 1,
		"Potuznik": 1,
		"Poul": 2,
		"Poulícek": 1,
		"Pour": 1,
		"Poustka": 1,
		"Pouzar": 1,
		"Pozdena": 1,
		"Pozivil": 4,
		"Prasek": 2,
		"Pravda": 3,
		"Pray": 1,
		"Prazak": 2,
		"Prazan": 2,
		"Prchal": 1,
		"Prcik": 1,
		"Precechtel": 2,
		"Preisinger": 1,
		"Preussler": 1,
		"Prevor": 1,
		"Pribyl": 8,
		"Prichodko": 2,
		"Pridal": 1,
		"Prihoda": 1,
		"Prikryl": 4,
		"Prinda": 1,
		"Privoznik": 1,
		"Prochazka": 10,
		"Procházka": 15,
		"Prokes": 3,
		"Prokop": 1,
		"Proks": 1,
		"Prokupek": 1,
		"Pronin": 1,
		"Prosek": 2,
		"Prospal": 1,
		"Pross": 1,
		"Prusak": 1,
		"Prusek": 4,
		"Pruzek": 1,
		"Przybyla": 2,
		"Psar": 1,
		"Psenicka": 4,
		"Psohlavec": 1,
		"Psota": 1,
		"Psurny": 1,
		"Psurný": 1,
		"Ptacek": 1,
		"Pucek": 2,
		"Puchala": 1,
		"Pufr": 1,
		"Puhony": 1,
		"Pulda": 2,
		"Pulpan": 1,
		"Pulpán": 1,
		"Purma": 1,
		"Puskar": 1,
		"Putz": 1,
		"Puza": 1,
		"Pycha": 1,
		"Pyrochta": 1,
		"Pytel": 1,
		"Pytlik": 2,
		"Pánek": 2,
		"Pérez": 1,
		"Písarík": 1,
		"Pöschl": 1,
		"Pýcha": 1,
		"Racansky": 2,
		"Racek": 1,
		"Rachunek": 2,
		"Racický": 1,
		"Racuk": 1,
		"Rada": 2,
		"Radil": 1,
		"Rados": 1,
		"Raichl": 1,
		"Rajek": 1,
		"Rajgl": 1,
		"Rajnoha": 1,
		"Rakus": 1,
		"Rakusan": 1,
		"Rambousek": 2,
		"Ramert": 1,
		"Ramik": 1,
		"Raska": 5,
		"Rasner": 1,
		"Raszka": 2,
		"Rasín": 1,
		"Raus": 2,
		"Redlich": 2,
		"Rehak": 10,
		"Rehor": 1,
		"Rehorek": 1,
		"Reichel": 4,
		"Reisnecker": 2,
		"Reitspies": 1,
		"Rejhon": 1,
		"Rejna": 1,
		"Rejthar": 1,
		"Remes": 1,
		"Remta": 1,
		"Rendla": 1,
		"Repa": 1,
		"Repik": 1,
		"Repka": 1,
		"Repík": 1,
		"Revaj": 1,
		"Rezabek": 1,
		"Rezac": 4,
		"Rezek": 2,
		"Reznar": 1,
		"Reznicek": 4,
		"Richtr": 1,
		"Ricka": 3,
		"Riedl": 2,
		"Riha": 6,
		"Rimmel": 1,
		"Rimsky": 1,
		"Rindos": 1,
		"Ripa": 1,
		"Rittich": 1,
		"Rizak": 1,
		"Rob": 2,
		"Rocak": 1,
		"Rod": 1,
		"Rodek": 1,
		"Rohacek": 1,
		"Rohan": 1,
		"Rohlik": 3,
		"Roj": 1,
		"Rolinek": 1,
		"Roman": 1,
		"Roncka": 1,
		"Rosa": 1,
		"Rosol": 1,
		"Rostejsky": 1,
		"Roubík": 1,
		"Rouha": 1,
		"Rous": 2,
		"Rousek": 6,
		"Routa": 4,
		"Rozhon": 1,
		"Rozlilek": 1,
		"Rozmarin": 1,
		"Rozsival": 1,
		"Rozsypal": 1,
		"Rozsíval": 1,
		"Rubacek": 1,
		"Rubes": 4,
		"Rubner": 1,
		"Rucki": 1,
		"Ruda": 1,
		"Rudl": 1,
		"Rudolf": 3,
		"Rudolph": 1,
		"Rudovský": 1,
		"Rulc": 1,
		"Rulik": 1,
		"Rulík": 1,
		"Ruml": 1,
		"Rusina": 1,
		"Rutar": 5,
		"Rutta": 1,
		"Ruzek": 1,
		"Ruzicka": 12,
		"Rybar": 1,
		"Rybnikár": 1,
		"Rybár": 1,
		"Rychlovský": 1,
		"Rychlík": 1,
		"Rykl": 1,
		"Rylich": 1,
		"Rymon": 1,
		"Rypar": 1,
		"Rysavy": 4,
		"Rysánek": 1,
		"Rákos": 1,
		"Réway": 1,
		"Ríha": 4,
		"Sabatka": 1,
		"Sabiniok": 1,
		"Sachl": 1,
		"Sachr": 1,
		"Safar": 1,
		"Safarik": 1,
		"Safin": 1,
		"Safranek": 1,
		"Safránek": 1,
		"Safár": 5,
		"Sailer": 1,
		"Sajdl": 2,
		"Sajdok": 1,
		"Sakalas": 1,
		"Saklein": 1,
		"Salak": 1,
		"Salda": 1,
		"Sale": 1,
		"Salek": 1,
		"Salficky": 1,
		"Salnikov": 1,
		"Samal": 1,
		"Samek": 1,
		"Samson": 1,
		"Sana": 1,
		"Sanc": 1,
		"Sander": 1,
		"Sanejstr": 1,
		"Santora": 1,
		"Sapousek": 1,
		"Sapovaliv": 1,
		"Sarman": 1,
		"Satava": 1,
		"Satek": 1,
		"Satny": 1,
		"Saur": 1,
		"Scafari": 1,
		"Scerban": 1,
		"Schacherl": 1,
		"Scheichlova": 1,
		"Schejbal": 1,
		"Scheuter": 1,
		"Schindler": 2,
		"Schleiss": 1,
		"Schlosser": 1,
		"Schmerda": 1,
		"Schmid": 1,
		"Schmidt": 1,
		"Schmied": 2,
		"Schmuk": 1,
		"Schmutz": 1,
		"Schnattinger": 1,
		"Schnierer": 1,
		"Schulmeister": 3,
		"Schusser": 1,
		"Schwamberger": 2,
		"Schwarz": 2,
		"Schön": 1,
		"Scislak": 1,
		"Scotka": 1,
		"Scurek": 1,
		"Seba": 4,
		"Sebela": 2,
		"Sebera": 1,
		"Sebesta": 2,
		"Sedenka": 1,
		"Sedivec": 1,
		"Sedivy": 4,
		"Sedlacek": 16,
		"Sedlak": 8,
		"Sedlácek": 2,
		"Sedlák": 4,
		"Seemann": 1,
		"Seidenglanz": 1,
		"Seidl": 3,
		"Seidler": 1,
		"Sejba": 2,
		"Sejc": 1,
		"Sejpal": 1,
		"Sekac": 1,
		"Sekanina": 1,
		"Sekera": 1,
		"Seliga": 1,
		"Sem": 1,
		"Semirad": 1,
		"Semorád": 1,
		"Semrad": 1,
		"Sencak": 1,
		"Senkerik": 1,
		"Sentiván": 1,
		"Sequens": 1,
		"Serafin": 1,
		"Sevc": 1,
		"Sevcik": 4,
		"Sevcu": 2,
		"Sevecek": 1,
		"Severa": 1,
		"Shanel": 1,
		"Shrbeny": 1,
		"Sic": 1,
		"Sichan": 1,
		"Sichtar": 2,
		"Sidak": 1,
		"Sidlik": 1,
		"Sieger": 1,
		"Sigmund": 1,
		"Sik": 2,
		"Sikl": 3,
		"Sikora": 2,
		"Silar": 2,
		"Siler": 1,
		"Silhan": 3,
		"Silhavy": 4,
		"Sima": 2,
		"Simak": 5,
		"Simanek": 1,
		"Simecek": 3,
		"Simek": 5,
		"Simicek": 1,
		"Simmons-Fischer": 1,
		"Simon": 5,
		"Simonek": 1,
		"Simonu": 1,
		"Simsalek": 1,
		"Simunek": 1,
		"Sindelar": 5,
		"Sindelek": 1,
		"Sindelka": 1,
		"Sindler": 1,
		"Sinkovsky": 1,
		"Sinkule": 1,
		"Sinu": 1,
		"Sipek": 1,
		"Sipla": 1,
		"Sir": 2,
		"Sirota": 1,
		"Sisak": 1,
		"Sisler": 3,
		"Sivek": 1,
		"Skacel": 2,
		"Skala": 1,
		"Skaloud": 2,
		"Skalsky": 1,
		"Skarda": 1,
		"Skarek": 1,
		"Skarka": 1,
		"Sklenar": 3,
		"Sklenicka": 3,
		"Sklenár": 1,
		"Sknouril": 1,
		"Skodik": 1,
		"Skok": 1,
		"Skokan": 3,
		"Skola": 1,
		"Skopal": 1,
		"Skorepa": 3,
		"Skorpik": 1,
		"Skoumal": 2,
		"Skrip": 1,
		"Skuhravy": 2,
		"Skuhravý": 1,
		"Skuhrovec": 2,
		"Skuratov": 1,
		"Skurek": 1,
		"Skvara": 1,
		"Skvarek": 1,
		"Skyba": 2,
		"Skála": 2,
		"Slaby": 4,
		"Slabý": 1,
		"Slachta": 1,
		"Slacik": 1,
		"Sladky": 1,
		"Sladký": 1,
		"Slahar": 1,
		"Slaicher": 1,
		"Slama": 1,
		"Slanina": 2,
		"Slansky": 3,
		"Slavata": 1,
		"Slavicek": 4,
		"Slavik": 4,
		"Slavkovsky": 1,
		"Slavícek": 1,
		"Slavík": 1,
		"Slechta": 1,
		"Slivko": 2,
		"Sliz": 1,
		"Sloboda": 1,
		"Slovacek": 3,
		"Slustik": 1,
		"Slustík": 1,
		"Sláma": 1,
		"Smach": 1,
		"Smajda": 1,
		"Smatana": 1,
		"Smejc": 1,
		"Smejkal": 4,
		"Smerda": 1,
		"Smerha": 1,
		"Smericka": 1,
		"Smetana": 1,
		"Smetanka": 1,
		"Smid": 5,
		"Smida": 1,
		"Smola": 2,
		"Smolenak": 1,
		"Smolik": 1,
		"Smolka": 4,
		"Smolko": 1,
		"Smuk": 1,
		"Smykal": 1,
		"Smítal": 4,
		"Snopek": 1,
		"Soban": 1,
		"Sobol": 2,
		"Sobotka": 2,
		"Socha": 1,
		"Sochor": 1,
		"Sochurek": 2,
		"Sojka": 1,
		"Sokol": 1,
		"Sokolik": 1,
		"Soldán": 1,
		"Solowski": 1,
		"Sorf": 1,
		"Soska": 1,
		"Sosnovec": 1,
		"Sotkovsky": 1,
		"Soucek": 2,
		"Soudek": 2,
		"Soukup": 11,
		"Sourek": 1,
		"Sousek": 1,
		"Soustal": 1,
		"Soustek": 1,
		"Sova": 1,
		"Sovik": 1,
		"Spacek": 10,
		"Spanel": 1,
		"Spanhel": 1,
		"Speierl": 1,
		"Spesny": 1,
		"Spevacek": 2,
		"Spilka": 2,
		"Spinka": 1,
		"Spirek": 2,
		"Spirik": 1,
		"Spratek": 1,
		"Sprynar": 1,
		"Spunar": 1,
		"Spurny": 1,
		"Spálenka": 1,
		"Sramek": 3,
		"Srbecký": 1,
		"Srdinko": 2,
		"Srek": 1,
		"Srnsky": 1,
		"Srotyr": 1,
		"Srsen": 1,
		"Srubar": 1,
		"Stach": 1,
		"Stafl": 1,
		"Stahl": 2,
		"Stajnc": 1,
		"Stajner": 1,
		"Stancik": 1,
		"Stancl": 1,
		"Stanek": 3,
		"Stangl": 1,
		"Stankovic": 1,
		"Stantien": 1,
		"Starka": 3,
		"Starustka": 1,
		"Stary": 3,
		"Starý": 2,
		"Stastka": 1,
		"Stastny": 8,
		"Stavicek": 1,
		"Stavjana": 1,
		"Stebel": 1,
		"Stebetak": 1,
		"Stedry": 1,
		"Stefka": 2,
		"Stehlik": 3,
		"Stehno": 1,
		"Steiner": 2,
		"Stejskal": 10,
		"Stekly": 1,
		"Stekr": 1,
		"Stencel": 1,
		"Stepan": 1,
		"Stepanchuk": 1,
		"Stepanek": 8,
		"Stepka": 1,
		"Stepánek": 2,
		"Sterba": 1,
		"Sterek": 1,
		"Stetina": 1,
		"Stezka": 1,
		"Stiak": 1,
		"Stibingr": 1,
		"Stiburek": 1,
		"Stieler": 1,
		"Stindl": 1,
		"Stipcak": 1,
		"Stipek": 4,
		"Stloukal": 2,
		"Stochl": 1,
		"Stodulka": 2,
		"Stohanzl": 4,
		"Stoklasa": 2,
		"Stola": 1,
		"Stolfa": 1,
		"Stolz": 1,
		"Storkan": 1,
		"Stovicek": 1,
		"Strache": 1,
		"Straka": 6,
		"Strakos": 1,
		"Strambersky": 1,
		"Stransky": 6,
		"Strapina": 1,
		"Stratil": 1,
		"Strba": 1,
		"Strecha": 2,
		"Strejcek": 1,
		"Stritesky": 1,
		"Strmen": 1,
		"Strnad": 5,
		"Strombach": 1,
		"Strondala": 1,
		"Stros": 1,
		"Struna": 1,
		"Strunz": 1,
		"Stránský": 5,
		"Stuchlik": 3,
		"Studeny": 1,
		"Studnický": 1,
		"Stulo": 1,
		"Stupka": 2,
		"Stínil": 1,
		"Stütz": 1,
		"Subr": 1,
		"Suchan": 3,
		"Suchanek": 3,
		"Suchy": 3,
		"Suchánek": 1,
		"Suchý": 4,
		"Suda": 1,
		"Suhaj": 1,
		"Suhajek": 1,
		"Suhrada": 1,
		"Suk": 2,
		"Sulak": 1,
		"Sulan": 1,
		"Sulc": 1,
		"Sulek": 1,
		"Sulgan": 1,
		"Suma": 1,
		"Sund": 1,
		"Suran": 1,
		"Surý": 1,
		"Susen": 1,
		"Sustr": 2,
		"Svacina": 1,
		"Svadlena": 1,
		"Svagrovsky": 1,
		"Svajda": 1,
		"Svancar": 1,
		"Svancara": 2,
		"Svarc": 1,
		"Svaricek": 1,
		"Svatuska": 1,
		"Svec": 7,
		"Svehla": 1,
		"Svejcar": 1,
		"Svejda": 2,
		"Svejkovsky": 2,
		"Svenkrt": 1,
		"Svetlik": 1,
		"Svik": 1,
		"Svitak": 1,
		"Svoboda": 25,
		"Svozil": 5,
		"Svrcek": 1,
		"Sykora": 5,
		"Synek": 3,
		"Sypecky": 1,
		"Syrovatko": 2,
		"Szabo": 1,
		"Szarowski": 1,
		"Szathmary": 1,
		"Szturc": 2,
		"Sáblík": 1,
		"Ségl": 1,
		"Síla": 1,
		"Süss": 1,
		"Sýkora": 3,
		"Taborsky": 1,
		"Talafa": 1,
		"Taliga": 1,
		"Tarnoczy": 1,
		"Tatar": 1,
		"Tatarcík": 1,
		"Taticek": 1,
		"Tecl": 2,
		"Tejko": 1,
		"Tejnor": 1,
		"Telesz": 1,
		"Teper": 1,
		"Teplý": 2,
		"Terc": 1,
		"Tesar": 1,
		"Tesarík": 1,
		"Tetur": 1,
		"Teuber": 2,
		"Theimer": 1,
		"Theodore": 1,
		"Thiel": 1,
		"Tichacek": 1,
		"Tichopad": 1,
		"Tichy": 4,
		"Tichý": 3,
		"Timko": 1,
		"Timura": 1,
		"Tintera": 1,
		"Titlbach": 1,
		"Tittl": 1,
		"Tlacil": 2,
		"Tmej": 1,
		"Tobias": 1,
		"Tobiska": 1,
		"Tobola": 2,
		"Tokaitsuk": 1,
		"Tolar": 1,
		"Toma": 2,
		"Tomajko": 2,
		"Toman": 3,
		"Tomanek": 1,
		"Tomas": 1,
		"Tomasek": 2,
		"Tomecek": 3,
		"Tomek": 3,
		"Tomes": 2,
		"Tomi": 1,
		"Tomica": 2,
		"Tomiczek": 1,
		"Tomiga": 1,
		"Tomis": 1,
		"Toms": 1,
		"Tomsa": 1,
		"Tomsik": 1,
		"Tomásek": 4,
		"Ton": 2,
		"Tondr": 1,
		"Topol": 2,
		"Topolancin": 1,
		"Topolansky": 1,
		"Tot": 1,
		"Totter": 1,
		"Toulec": 1,
		"Trachta": 2,
		"Trajkov": 1,
		"Tramba": 1,
		"Trapl": 1,
		"Travnicek": 1,
		"Trc": 1,
		"Trebicky": 1,
		"Trefil": 1,
		"Trefny": 1,
		"Trefný": 1,
		"Trejbal": 3,
		"Trlicik": 1,
		"Trnavsky": 2,
		"Trnavský": 1,
		"Trnka": 4,
		"Trojna": 2,
		"Troska": 1,
		"Trubac": 1,
		"Trunda": 1,
		"Tucek": 2,
		"Tuhy": 1,
		"Tuhácek": 1,
		"Tulacek": 1,
		"Tulacka": 1,
		"Tuma": 8,
		"Turecek": 2,
		"Turek": 5,
		"Turena": 1,
		"Turon": 1,
		"Tusl": 1,
		"Tvrdik": 2,
		"Tvrdy": 1,
		"Tvrdík": 2,
		"Tvrznik": 2,
		"Tvrzník": 1,
		"Twardzik": 1,
		"Tykal": 1,
		"Typl": 1,
		"Táborský": 1,
		"Týr": 1,
		"Ubl": 1,
		"Udrzal": 1,
		"Uher": 2,
		"Uherek": 1,
		"Uhlir": 1,
		"Uhlík": 1,
		"Uhricek": 1,
		"Uhrin": 2,
		"Ujcík": 1,
		"Ujfalusi": 1,
		"Ulbricht": 1,
		"Ulehla": 2,
		"Ulrych": 1,
		"Ungr": 1,
		"Unzeitig": 1,
		"Uram": 1,
		"Urbacka": 1,
		"Urban": 9,
		"Urbanec": 1,
		"Urbanek": 2,
		"Urbisch": 1,
		"Urbánek": 1,
		"Uricar": 1,
		"Uridil": 1,
		"Urie": 1,
		"Uvira": 1,
		"Vacha": 2,
		"Vachovec": 1,
		"Vachun": 1,
		"Vachutka": 1,
		"Vacin": 1,
		"Vaclavek": 1,
		"Vaclavicek": 1,
		"Vaculik": 2,
		"Vaculík": 1,
		"Vagner": 1,
		"Vajner": 2,
		"Vala": 4,
		"Valach": 1,
		"Valasek": 3,
		"Valchar": 1,
		"Valek": 1,
		"Valenta": 5,
		"Valouch": 1,
		"Valsky": 1,
		"Valta": 1,
		"Valus": 1,
		"Valusiak": 1,
		"Valvoda": 1,
		"Vana": 5,
		"Vandas": 2,
		"Vanecek": 4,
		"Vanek": 6,
		"Vanha": 1,
		"Vanicek": 2,
		"Vankovsky": 1,
		"Vantuch": 1,
		"Vanícek": 2,
		"Varada": 1,
		"Varadi": 1,
		"Varady": 1,
		"Varecka": 1,
		"Vareka": 1,
		"Varga": 1,
		"Varvarovsky": 1,
		"Vasek": 3,
		"Vasenka": 1,
		"Vasicek": 4,
		"Vasilev": 1,
		"Vasilj": 1,
		"Vasícek": 1,
		"Vavra": 5,
		"Vavrecka": 1,
		"Vavrena": 1,
		"Vavrik": 2,
		"Vavrouch": 1,
		"Vazac": 1,
		"Veber": 2,
		"Vechet": 1,
		"Vedral": 2,
		"Vehovsky": 2,
		"Vejmelka": 2,
		"Vejvoda": 3,
		"Velcovska": 1,
		"Velcovský": 1,
		"Velecký": 1,
		"Velek": 1,
		"Velicka": 1,
		"Velikovsky": 1,
		"Venc": 1,
		"Vencl": 1,
		"Veneny": 1,
		"Ventus": 1,
		"Verbescuk": 1,
		"Vermirovsky": 1,
		"Vesecký": 1,
		"Veselsky": 1,
		"Vesely": 5,
		"Veselý": 5,
		"Vich": 1,
		"Vidner": 1,
		"Viedemann": 2,
		"Viková": 1,
		"Vildomec": 1,
		"Vildumetz": 1,
		"Vilem": 1,
		"Vimmer": 1,
		"Vincour": 1,
		"Vinklarek": 1,
		"Vinkler": 1,
		"Vins": 3,
		"Visnak": 1,
		"Visnák": 2,
		"Vit": 1,
		"Vitak": 1,
		"Vitek": 6,
		"Vitouch": 2,
		"Vlach": 11,
		"Vladar": 1,
		"Vladyka": 1,
		"Vlasak": 3,
		"Vlastnik": 1,
		"Vlcek": 7,
		"Vlk": 2,
		"Voboril": 1,
		"Vochozka": 1,
		"Vochvest": 1,
		"Voderacky": 1,
		"Vodicka": 2,
		"Vodný": 1,
		"Vogel": 1,
		"Vogeltanz": 1,
		"Vogl": 1,
		"Vojacek": 4,
		"Vojan": 1,
		"Vojcak": 1,
		"Vojir": 1,
		"Vojkuvka": 2,
		"Vojtek": 1,
		"Vojtovic": 1,
		"Vokac": 1,
		"Volas": 1,
		"Volejnicek": 1,
		"Volena": 1,
		"Volevecky": 1,
		"Volf": 5,
		"Volke": 1,
		"Volodin": 1,
		"Volosin": 1,
		"Volrab": 1,
		"Volráb": 2,
		"Vomacka": 2,
		"Vondracek": 3,
		"Vondras": 1,
		"Vondruska": 1,
		"Vondrácek": 2,
		"Vonka": 1,
		"Vopat": 8,
		"Vopelka": 1,
		"Vopravil": 1,
		"Voracek": 2,
		"Vorel": 1,
		"Vorisek": 1,
		"Vosatko": 1,
		"Vosmik": 2,
		"Vosmík": 1,
		"Vosta": 1,
		"Vostarek": 2,
		"Vostinak": 1,
		"Vostrak": 1,
		"Vosvrda": 1,
		"Votapek": 1,
		"Votoupal": 1,
		"Vovsik": 1,
		"Vozak": 1,
		"Vozenilek": 2,
		"Vrabel": 1,
		"Vracovský": 1,
		"Vrana": 1,
		"Vrba": 4,
		"Vrbas": 1,
		"Vrbecký": 1,
		"Vrbka": 1,
		"Vrbovec": 1,
		"Vrhel": 1,
		"Vrtek": 1,
		"Vrzal": 3,
		"Vráblík": 1,
		"Vrána": 4,
		"Vsetecka": 2,
		"Vybiral": 1,
		"Vydra": 3,
		"Vyhlidal": 2,
		"Vymyslicky": 1,
		"Vyoralek": 1,
		"Vyroubal": 2,
		"Vyrubalik": 1,
		"Vyrut": 1,
		"Vyskocil": 1,
		"Vystrcil": 1,
		"Vyvial": 2,
		"Vácha": 1,
		"Váchal": 2,
		"Vágner": 1,
		"Válka": 1,
		"Vápeník": 2,
		"Vícha": 1,
		"Vítek": 4,
		"Wagner": 1,
		"Wanecki": 1,
		"Wardas": 2,
		"Wasserbauer": 1,
		"Weber": 1,
		"Weinert": 1,
		"Weinhold": 1,
		"Weintritt": 2,
		"Weiss": 1,
		"Welser": 1,
		"Wendelin": 1,
		"Werbik": 1,
		"Werner": 1,
		"Wesley": 1,
		"Wesserbauer": 1,
		"Wildumetz": 1,
		"Will": 1,
		"Willmann": 1,
		"Winkelhöfer": 1,
		"Wlodara": 1,
		"Wojnar": 1,
		"Wolf": 1,
		"Xhekaj": 2,
		"Yashkin": 1,
		"Yeol Oh": 1,
		"Zaba": 1,
		"Zabloudil": 1,
		"Zabransky": 2,
		"Zacek": 1,
		"Zacha": 1,
		"Zachar": 1,
		"Zacharias": 1,
		"Zachrla": 1,
		"Zadina": 4,
		"Zadrazil": 2,
		"Zahejsky": 1,
		"Zahradnícek": 1,
		"Zajan": 1,
		"Zajdlik": 1,
		"Zajic": 1,
		"Zajicek": 3,
		"Zajíc": 1,
		"Zak": 4,
		"Zakutanský": 1,
		"Zalcik": 1,
		"Zalud": 1,
		"Zamecnik": 1,
		"Zapletal": 3,
		"Zaruba": 2,
		"Zatloukal": 1,
		"Zatovic": 1,
		"Zavora": 1,
		"Zavoral": 1,
		"Zavrel": 3,
		"Zayml": 1,
		"Zbanek": 1,
		"Zboril": 4,
		"Zbozínek": 1,
		"Zdara": 1,
		"Zdenek": 1,
		"Zderadicka": 2,
		"Zdrahal": 3,
		"Zdráhal": 1,
		"Zduba": 1,
		"Zdárský": 1,
		"Zecha": 1,
		"Zedek": 2,
		"Zeithaml": 1,
		"Zejda": 1,
		"Zejdl": 1,
		"Zelenka": 3,
		"Zelezny": 2,
		"Zelingr": 1,
		"Zelinka": 1,
		"Zeman": 12,
		"Zembol": 1,
		"Zemlicka": 2,
		"Zenisek": 2,
		"Zenker": 1,
		"Zevl": 1,
		"Zhánal": 1,
		"Zich": 1,
		"Zidek": 3,
		"Zidlicky": 2,
		"Zielinski": 1,
		"Zika": 1,
		"Zikmund": 3,
		"Zima": 1,
		"Zimmer": 1,
		"Zimovcak": 1,
		"Zizka": 6,
		"Zlatnicky": 1,
		"Zmeskal": 1,
		"Zmola": 1,
		"Zmrhal": 1,
		"Zohorna": 4,
		"Zolnaj": 1,
		"Zoubek": 1,
		"Zouhar": 1,
		"Zovinec": 1,
		"Zrzavecky": 1,
		"Zubicek": 2,
		"Zucker": 1,
		"Zukal": 1,
		"Zukovskij": 1,
		"Zumr": 1,
		"Zurek": 5,
		"Zvejska": 1,
		"Zverina": 1,
		"Zyla": 1,
		"Zábojník": 1,
		"Zábranský": 4,
		"Záhorec": 1,
		"Záleský": 1,
		"Zámorský": 1,
		"Záruba": 1,
		"Zátopek": 1,
		"Zídek": 1,
		"Zörkler": 1
	}
}