{
	"forenames": {
		"Abai": 1,
		"Abay": 1,
		"Abdurrakhim": 1,
		"Abilmansur": 1,
		"Abylaikhan": 2,
		"Abylkhair": 1,
		"Abzal": 1,
		"Adam": 2,
		"Adil": 3,
		"Adilet": 1,
		"Adilkhan": 2,
		"Adilzhan": 2,
		"Adis": 1,
		"Adiyat": 1,
		"Aibat": 1,
		"Aibolsyn": 1,
		"Aidar": 2,
		"Aidos": 1,
		"Aidyn": 2,
		"Ainarbek": 1,
		"Aituar": 1,
		"Aitugan": 1,
		"Akezhan": 1,
		"Akhmad": 2,
		"Alaidar": 1,
		"Alan": 4,
		"Albert": 4,
		"Aldiyar": 5,
		"Aleksandr": 4,
		"Aleksei": 1,
		"Alexander": 50,
		"Alexei": 17,
		"Ali": 3,
		"Alikhan": 5,
		"Alisher": 3,
		"Alkham": 1,
		"Almas": 1,
		"Almaz": 1,
		"Almir": 1,
		"Altair": 1,
		"Amandyk": 1,
		"Amir": 6,
		"Amirkhan": 1,
		"Anatoli": 3,
		"Andrei": 24,
		"Ansar": 4,
		"Anton": 3,
		"Argyn": 2,
		"Aristarkh": 1,
		"Arkadi": 1,
		"Arlan": 1,
		"Arman": 3,
		"Arnur": 1,
		"Arsen": 6,
		"Arseni": 2,
		"Arslan": 1,
		"Artemi": 2,
		"Artur": 11,
		"Artyom": 21,
		"Arystan": 2,
		"Asanali": 3,
		"Askhat": 2,
		"Aslan": 2,
		"Batyr": 3,
		"Batyrlan": 1,
		"Bauyrzhan": 1,
		"Beibarys": 2,
		"Bekarys": 1,
		"Bekbolat": 1,
		"Beknur": 1,
		"Beksultan": 1,
		"Bertan": 1,
		"Birzhan": 1,
		"Bogdan": 10,
		"Bolat": 2,
		"Boris": 2,
		"Bukhar": 1,
		"Curtis": 1,
		"Dair": 1,
		"Damir": 4,
		"Danai": 1,
		"Danial": 2,
		"Daniel": 4,
		"Daniiar": 1,
		"Daniil": 16,
		"Danil": 11,
		"Danila": 3,
		"Daniyal": 1,
		"Daniyar": 5,
		"Darkhan": 2,
		"Darmen": 2,
		"Darren": 1,
		"Dastan": 1,
		"Daulet": 1,
		"David": 5,
		"Davlat": 1,
		"Davyd": 1,
		"Demid": 1,
		"Denir": 1,
		"Denis": 14,
		"Diar": 1,
		"Dias": 4,
		"Didar": 2,
		"Dilmukhammed": 1,
		"Dimitri": 1,
		"Dinmukhamed": 2,
		"Dinmukhammet": 1,
		"Dmitri": 24,
		"Dmitri A.": 1,
		"Dmitrii": 2,
		"Doszhan": 1,
		"Dulat": 3,
		"Dzhokhar": 1,
		"Eduard": 6,
		"Eldos": 1,
		"Elzhan": 1,
		"Emil": 1,
		"Emir": 1,
		"Erasyl": 4,
		"Erdaulet": 1,
		"Erik": 1,
		"Ermukhamed": 1,
		"Ernur": 1,
		"Evgeni": 1,
		"Evgeny": 1,
		"Filipp": 1,
		"Fyodor": 3,
		"Galym": 1,
		"Galymzhan": 1,
		"Georgi": 1,
		"Gleb": 11,
		"Gordei": 1,
		"Grigori": 1,
		"Ibragim": 2,
		"Ignat": 3,
		"Igor": 13,
		"Il'ia": 1,
		"Il'ias": 1,
		"Ildar": 1,
		"Ildus": 1,
		"Ilgiz": 1,
		"Ilkhyon": 1,
		"Ilya": 19,
		"Ilyas": 3,
		"Isa": 1,
		"Ivan": 19,
		"Ivan I.": 1,
		"Jelal-ad-Din": 1,
		"Jesse": 1,
		"Kairat": 2,
		"Kamal": 1,
		"Kanat": 3,
		"Karim": 2,
		"Kayrat": 1,
		"Khakim": 1,
		"Khaknazar": 1,
		"Kirill": 21,
		"Klimenti": 1,
		"Konstantin": 15,
		"Kornei": 1,
		"Kuanysh": 1,
		"Leonid": 5,
		"Lev": 3,
		"Madi": 2,
		"Madikhan": 1,
		"Madiyar": 1,
		"Makei": 1,
		"Maksat": 1,
		"Maksim": 2,
		"Mansur": 1,
		"Marat": 2,
		"Mark": 3,
		"Marsel": 1,
		"Matvei": 10,
		"Maxim": 25,
		"Mazhit": 1,
		"Meirzhan": 1,
		"Mikhael": 1,
		"Mikhail": 15,
		"Miras": 1,
		"Miron": 1,
		"Miroslav": 1,
		"Mnir": 1,
		"Mstislav": 1,
		"Mukhit": 1,
		"Musa": 1,
		"Nariman": 1,
		"Nikita": 44,
		"Nikita Al.": 1,
		"Nikolai": 6,
		"Nurali": 3,
		"Nurbol": 1,
		"Nurdaulet": 1,
		"Nurislam": 1,
		"Nurlan": 1,
		"Nurzhan": 1,
		"Oleg": 7,
		"Olzhas": 1,
		"Oskar": 1,
		"Pantelei": 1,
		"Pavel": 11,
		"Platon": 1,
		"Radion": 1,
		"Radmir": 1,
		"Rakhimbek": 1,
		"Rasul": 1,
		"Ratibor": 1,
		"Ratmir": 1,
		"Raty": 1,
		"Rauan": 1,
		"Raul": 1,
		"Rinat": 1,
		"Rodion": 3,
		"Roman": 20,
		"Rostislav": 1,
		"Ruslan": 11,
		"Rustam": 1,
		"Saken": 2,
		"Samat": 2,
		"Samir": 1,
		"Sanzhar": 4,
		"Saveli": 4,
		"Sayan": 1,
		"Sayat": 1,
		"Semyon": 5,
		"Sergei": 20,
		"Sergey": 3,
		"Serik": 2,
		"Sonmin": 1,
		"Spartak": 1,
		"Stanislav": 10,
		"Stepan": 3,
		"Subkhanberdy": 1,
		"Suleimen": 1,
		"Sultanbek": 1,
		"Svyatoslav": 2,
		"Tair": 3,
		"Talgat": 3,
		"Tamerlan": 8,
		"Tamirlan": 1,
		"Tanirkhan": 1,
		"Tarlan": 1,
		"Temirlan": 3,
		"Tigran": 2,
		"Tikhon": 2,
		"Timofei": 1,
		"Timur": 12,
		"Tleubergen": 1,
		"Tlieuberdi": 1,
		"Turar": 1,
		"Vadim": 7,
		"Valeri": 5,
		"Valerii": 2,
		"Vasily": 1,
		"Velor": 1,
		"Viacheslav": 1,
		"Viktor": 8,
		"Vitali": 3,
		"Vitalii": 1,
		"Vitaly": 1,
		"Vladimir": 15,
		"Vladislav": 18,
		"Vladislav I.": 1,
		"Vsevolod": 1,
		"Vyacheslav": 5,
		"Yan": 5,
		"Yaroslav": 6,
		"Yegor": 12,
		"Yelisei": 2,
		"Yerlan": 1,
		"Yernar": 1,
		"Yevgeni": 8,
		"Yevgeny": 1,
		"Yurgis": 1,
		"Yuri": 4,
		"Yusup": 1,
		"Zakhar": 2,
		"Zhaken": 1,
		"Zhakhanger": 1,
		"Zhakhangir": 1,
		"Zhanbolat": 1,
		"Zhangir": 1,
		"Zhangirkhan": 1,
		"Zhanibek": 1,
		"Zhantore": 1,
		"Zhuken": 1
	},
	"surnames": {
		"Abay": 1,
		"Abdenov": 1,
		"Abdrakhmanov": 1,
		"Abdualiev": 1,
		"Abdullin": 1,
		"Abenov": 1,
		"Abildin": 1,
		"Abishev": 1,
		"Adilbek": 1,
		"Aflitonov": 1,
		"Aglanbekov": 1,
		"Agoshkov": 1,
		"Aiboluly": 1,
		"Aidukov": 1,
		"Aimagambet": 1,
		"Aitmagambetov": 1,
		"Akhalbekov": 1,
		"Akhmedyarov": 1,
		"Akhmetov": 1,
		"Akmaldinov": 2,
		"Akolzin": 1,
		"Akpirganov": 1,
		"Aktayev": 1,
		"Akulinin": 1,
		"Aldabergenov": 1,
		"Aldongar": 1,
		"Alexandrov": 4,
		"Alexentsev": 1,
		"Alibayev": 1,
		"Alibek": 1,
		"Alikhan": 1,
		"Allamov": 1,
		"Alpkarin": 1,
		"Alpysbayev": 1,
		"Altukhov": 1,
		"Amangali": 1,
		"Amangaliyev": 1,
		"Amangeldy": 1,
		"Amengeldy": 1,
		"Aminov": 1,
		"Amirbekov": 1,
		"Amirzhanov": 1,
		"Amyrkanov": 1,
		"Ananichev": 2,
		"Andrusenko": 1,
		"Antipin": 1,
		"Antipov": 3,
		"Antropov": 1,
		"Antselm": 1,
		"Antsiferov": 1,
		"Anufriyev": 1,
		"Apasov": 1,
		"Argokov": 1,
		"Argymabayev": 1,
		"Arkhipov": 1,
		"Artamonov": 1,
		"Artemyev": 1,
		"Artyushin": 1,
		"Asanov": 1,
		"Asetov": 1,
		"Ashirbai": 1,
		"Askatuly": 1,
		"Astrakhantsev": 1,
		"Asukhanov": 1,
		"Atakhanov": 1,
		"Aubakirov": 3,
		"Auyezbay": 1,
		"Avdeyenko": 1,
		"Azizi": 1,
		"Azovskii": 2,
		"Babenko": 2,
		"Babeshko": 1,
		"Babichev": 1,
		"Bagitzhanov": 1,
		"Baidek": 2,
		"Baizhanov": 2,
		"Bakyt": 1,
		"Balanchik": 1,
		"Barulin": 1,
		"Bashirov": 1,
		"Batrun": 1,
		"Bazanov": 1,
		"Bazhenov": 1,
		"Bazko": 1,
		"Bazunts": 1,
		"Beck": 1,
		"Beisembayev": 1,
		"Beisembiyev": 1,
		"Bekbayev": 1,
		"Beketayev": 1,
		"Bekeyev": 1,
		"Belan": 2,
		"Belokonsky": 1,
		"Belous": 1,
		"Belyakov": 1,
		"Belyayev": 1,
		"Berezensky": 1,
		"Bessonov": 1,
		"Bezborodov": 1,
		"Bigarinov": 1,
		"Bilimbayev": 1,
		"Blacker": 1,
		"Blank": 1,
		"Blokhin": 1,
		"Bogdanov": 1,
		"Boiko": 1,
		"Boitsov": 1,
		"Bolat": 1,
		"Bolgov": 1,
		"Bolshedvorsky": 1,
		"Bolyakin": 2,
		"Bondarenko": 1,
		"Bopp": 1,
		"Borisevich": 1,
		"Borisov": 1,
		"Borovikov": 3,
		"Borovkov": 1,
		"Botishchev": 1,
		"Boyarkin": 1,
		"Bozhenov": 1,
		"Bozhko": 1,
		"Breus": 1,
		"Britikov": 1,
		"Bukar": 1,
		"Burabay": 1,
		"Burdelyov": 1,
		"Burnashov": 1,
		"Burtsev": 1,
		"Butenko": 1,
		"Buyalsky": 3,
		"Bykov": 3,
		"Chakenov": 1,
		"Chalkin": 1,
		"Chaporov": 1,
		"Chekalin": 1,
		"Chelaidyuk": 1,
		"Chelyuk": 1,
		"Chepyshkin": 1,
		"Cherepanov": 1,
		"Cherkasov": 1,
		"Chernei": 1,
		"Chernikov": 1,
		"Chernysh": 1,
		"Chokparov": 1,
		"Chuklinov": 1,
		"Chukreyev": 1,
		"Daniyar": 3,
		"Darkhan": 1,
		"Dauletaliyev": 1,
		"Dauletiyar": 1,
		"Dauletov": 1,
		"Dauylbay": 1,
		"Davletshin": 1,
		"Demirdelen": 1,
		"Denisov": 1,
		"Deppershmidt": 1,
		"Dide": 1,
		"Dietz": 1,
		"Dikhanbek": 1,
		"Dolganov": 1,
		"Domrachev": 1,
		"Dosmagambet": 1,
		"Dosmagambetov": 4,
		"Dronov": 1,
		"Drovosekov": 1,
		"Dubinkin": 1,
		"Dubinskas": 1,
		"Dubovich": 1,
		"Dubrovin": 1,
		"Dudarkiyev": 1,
		"Duplyakin": 1,
		"Durglishvili": 1,
		"Dvurechensky": 2,
		"Dyachenko": 1,
		"Dyomin": 1,
		"Dzhaukparov": 1,
		"Dzhunusov": 1,
		"Dück": 1,
		"Eldes": 1,
		"Engel": 3,
		"Erbulat": 1,
		"Ershtein": 1,
		"Erzhigit": 1,
		"Esen": 1,
		"Fanaylov": 1,
		"Fast": 1,
		"Fatykhov": 1,
		"Feoktistov": 1,
		"Filimonov": 1,
		"Filippenko": 1,
		"Filippov": 2,
		"Finonchenko": 6,
		"Firsa": 1,
		"Fokin": 2,
		"Franskevich": 1,
		"Frolov": 1,
		"Fyodorov": 1,
		"Gabazov": 1,
		"Gabdrakhmanov": 1,
		"Gabdulin": 1,
		"Gabdullin": 2,
		"Gafarov": 1,
		"Gafurov": 1,
		"Gaitamirov": 1,
		"Gaitov": 1,
		"Gareyev": 1,
		"Gasnikov": 2,
		"Gatin": 1,
		"Gatiyatov": 1,
		"Gavrilenko": 1,
		"Gebel": 1,
		"Gerasimov": 1,
		"Giganov": 1,
		"Gizatulin": 1,
		"Glavyuk": 1,
		"Glotov": 1,
		"Glukhikh": 1,
		"Golovashchenko": 1,
		"Gorban": 1,
		"Gordin": 1,
		"Gorozhaninov": 1,
		"Gostyushev": 1,
		"Grafkin": 1,
		"Grass": 1,
		"Grebenschikov": 1,
		"Grebenshchikov": 1,
		"Grents": 1,
		"Gridasov": 1,
		"Gridchin": 1,
		"Grigoryev": 1,
		"Grokhotov": 1,
		"Gromov": 3,
		"Gross": 1,
		"Gryaznov": 1,
		"Gulayev": 1,
		"Guly": 1,
		"Gumar": 1,
		"Gurin": 1,
		"Gurinovich": 1,
		"Guryev": 1,
		"Gusakov": 1,
		"Guseinov": 5,
		"Ibraev": 1,
		"Ibragim": 1,
		"Ibragimov": 2,
		"Ibrayev": 1,
		"Igushkin": 1,
		"Ikonnikov": 1,
		"Ilyas": 1,
		"Ilyasov": 1,
		"Ilyichyov": 1,
		"Imashev": 1,
		"Indyukov": 1,
		"Isa": 1,
		"Ishchenko": 2,
		"Ishmakov": 1,
		"Ishmametyev": 1,
		"Ismagilov": 1,
		"Ismailov": 1,
		"Istomin": 2,
		"Ivanishchev": 1,
		"Ivannikov": 1,
		"Ivanov": 3,
		"Ivanovsky": 2,
		"Kabatayev": 1,
		"Kabduali": 1,
		"Kadenov": 1,
		"Kadyrov": 1,
		"Kaibelev": 1,
		"Kairgeldy": 1,
		"Kairov": 1,
		"Kairtinov": 1,
		"Kaiyrzhan": 2,
		"Kakenov": 1,
		"Kalelkhan": 1,
		"Kalinichenko": 1,
		"Kaliyev": 1,
		"Kalkabek": 1,
		"Kalmykov": 1,
		"Kambarov": 1,
		"Kankin": 1,
		"Karatayev": 3,
		"Karpov": 2,
		"Karshygayev": 1,
		"Kasatkin": 1,
		"Kasenov": 1,
		"Katasonov": 1,
		"Katkov": 1,
		"Kazachenko": 1,
		"Kazbekov": 1,
		"Kazhibekov": 1,
		"Kenesbay": 1,
		"Kentayev": 1,
		"Kenzhegali": 1,
		"Khafarov": 1,
		"Khan": 1,
		"Khanzhin": 1,
		"Kharchenko": 1,
		"Khasenov": 3,
		"Khiduanov": 1,
		"Khizhnichenko": 3,
		"Khoroshev": 1,
		"Khramtsov": 1,
		"Khripkov": 1,
		"Khudyakov": 1,
		"Khusainov": 1,
		"Kim": 5,
		"Kindyakov": 1,
		"Kireyev": 2,
		"Kirgizbayev": 1,
		"Kirinevich": 1,
		"Kisel": 1,
		"Kiselyov": 3,
		"Kitarov": 1,
		"Kitchenko": 1,
		"Kizekpayev": 1,
		"Kladov": 1,
		"Kleshchenko": 1,
		"Klimakhin": 1,
		"Klimenko": 1,
		"Klimov": 1,
		"Klochanov": 1,
		"Knyazev": 1,
		"Koledayev": 1,
		"Kolesnik": 1,
		"Kolesnikov": 2,
		"Kolodyuk": 1,
		"Kolomytsev": 1,
		"Kolyuzhny": 1,
		"Komarov": 1,
		"Komissarov": 1,
		"Konochkin": 3,
		"Konrady": 1,
		"Kontuganov": 1,
		"Konus": 1,
		"Koptelov": 1,
		"Korabeynikov": 1,
		"Korchagin": 1,
		"Korennik": 1,
		"Koreshkov": 3,
		"Korneyev": 1,
		"Korniyenko": 1,
		"Korolinsky": 1,
		"Korolyov": 1,
		"Korotkikh": 1,
		"Korotkov": 1,
		"Korsakov": 1,
		"Korshkov": 2,
		"Koshelev": 1,
		"Koshevnik": 1,
		"Koshurin": 1,
		"Kostenko": 1,
		"Kostoyev": 1,
		"Kostyukov": 1,
		"Kotlobayev": 1,
		"Koval": 1,
		"Kovalenko": 1,
		"Kovzalov": 1,
		"Kozhemyako": 1,
		"Kozhukhovsky": 1,
		"Kozorez": 1,
		"Kozybayev": 1,
		"Kozynets": 1,
		"Kramarenko": 1,
		"Kravchenko": 1,
		"Kravtsov": 1,
		"Kritsin": 2,
		"Krivomazov": 1,
		"Kruglov": 1,
		"Krutokhvostov": 1,
		"Krutsky": 1,
		"Krylov": 1,
		"Kuat": 1,
		"Kubatayev": 1,
		"Kuchin": 1,
		"Kuchkovsky": 1,
		"Kuchma": 2,
		"Kudimov": 1,
		"Kudryavtsev": 1,
		"Kudyarov": 1,
		"Kukeev": 1,
		"Kukushkin": 1,
		"Kulakov": 1,
		"Kuminov": 2,
		"Kunishnikov": 1,
		"Kurnosenko": 1,
		"Kursakbayev": 1,
		"Kurshuk": 1,
		"Kutko": 1,
		"Kuzmin": 1,
		"Kydyrbay": 1,
		"Lagunov": 1,
		"Lakiza": 1,
		"Larikov": 1,
		"Layurov": 1,
		"Lazarenko": 1,
		"Lazarev": 1,
		"Letov": 1,
		"Leuta": 1,
		"Levchenko": 1,
		"Levkovets": 1,
		"Li": 1,
		"Libov": 1,
		"Ligay": 1,
		"Likhotnikov": 1,
		"Linnik": 1,
		"Lipayev": 1,
		"Lipin": 1,
		"Litvintsev": 2,
		"Logvin": 1,
		"Lomako": 1,
		"Lopukhov": 1,
		"Loria": 2,
		"Lukavenko": 1,
		"Lyapunov": 2,
		"Lytkin": 1,
		"Lyubchenko": 1,
		"Makarintsev": 1,
		"Makarov": 1,
		"Makeyev": 1,
		"Makhamadeyev": 1,
		"Makhinko": 1,
		"Makutsky": 1,
		"Makysh": 1,
		"Malikov": 1,
		"Maltsev": 1,
		"Mambetaliyev": 1,
		"Manash": 1,
		"Manazhanov": 1,
		"Mangisbayev": 1,
		"Manuilov": 1,
		"Marat": 1,
		"Marinin": 1,
		"Marinov": 1,
		"Markabayev": 1,
		"Markelov": 1,
		"Mashinets": 1,
		"Massen": 1,
		"Matrosov": 1,
		"Matveyev": 1,
		"Maximov": 1,
		"Mazbaev": 2,
		"Mazur": 1,
		"Medvedev": 1,
		"Medvedkov": 1,
		"Meider": 1,
		"Meiram": 1,
		"Meirman": 1,
		"Melekhov": 1,
		"Melis": 1,
		"Melnikov": 2,
		"Menshenin": 1,
		"Merzlikin": 1,
		"Migunov": 1,
		"Mikhailis": 2,
		"Mikhailov": 2,
		"Mikhalchenko": 1,
		"Mikheyev": 1,
		"Mikushin": 1,
		"Miller": 1,
		"Mindubayev": 1,
		"Miroshnichenko": 1,
		"Mirzakhmatov": 1,
		"Mitenkov": 1,
		"Mogilnikov": 1,
		"Morozhnikov": 1,
		"Mozzherin": 1,
		"Mukanov": 3,
		"Mukashev": 1,
		"Mukhamediyarov": 1,
		"Mukhamedkaiyr": 1,
		"Mukhametov": 1,
		"Mullerov": 1,
		"Murataliuly": 1,
		"Muratov": 1,
		"Murin": 1,
		"Musataev": 1,
		"Musorov": 1,
		"Mussaibekov": 1,
		"Myasnikov": 1,
		"Myrzatayev": 1,
		"Myshlyayev": 1,
		"Nabokov": 1,
		"Nadeikin": 1,
		"Namestnikov": 1,
		"Nazarov": 1,
		"Nechviyenko": 1,
		"Neifeld": 1,
		"Neumyvaikin": 1,
		"Nevstruyev": 1,
		"Nigmatullin": 1,
		"Nikitin": 3,
		"Nikulin": 1,
		"Nurek": 1,
		"Nurgaliev": 2,
		"Nuriyev": 1,
		"Nurkanov": 2,
		"Nurkenov": 1,
		"Nurlan": 2,
		"Nursultanov": 1,
		"Nurzhangali": 1,
		"Nurzhanov": 1,
		"Nuserbaev": 2,
		"Oldenburger": 1,
		"Omarbekov": 1,
		"Omelkovets": 1,
		"Omelnitsky": 1,
		"Omirbekov": 1,
		"Orazbayev": 1,
		"Orazgali": 1,
		"Orazov": 1,
		"Orekhov": 1,
		"Oreshko": 1,
		"Osenin": 1,
		"Osipov": 1,
		"Osokin": 1,
		"Ospanov": 1,
		"Otoudinov": 1,
		"Pak": 1,
		"Pakholenko": 1,
		"Palmtag": 1,
		"Panchenko": 1,
		"Panin": 1,
		"Panyukov": 1,
		"Parkhomenko": 2,
		"Parshin": 1,
		"Pashkovsky": 1,
		"Pavlenko": 1,
		"Pavlov": 1,
		"Pelevin": 1,
		"Perkin": 1,
		"Perminov": 1,
		"Permyakov": 1,
		"Pertsev": 1,
		"Pestov": 1,
		"Petrasyuk": 1,
		"Petrenko": 1,
		"Petrov": 1,
		"Pidyashov": 1,
		"Pinidi": 1,
		"Pishchulin": 5,
		"Plotnikov": 3,
		"Polat": 1,
		"Polenov": 1,
		"Polishchuk": 2,
		"Polokhov": 1,
		"Poloshkov": 1,
		"Polovnikov": 1,
		"Polozhukhno": 1,
		"Polyakov": 1,
		"Ponomaryov": 3,
		"Popov": 1,
		"Potapov": 2,
		"Potyrka": 1,
		"Presnov": 1,
		"Pritsker": 1,
		"Prokhorov": 1,
		"Prokopenko": 2,
		"Pugachyov": 1,
		"Pupkov": 1,
		"Pushkaryov": 6,
		"Pushkov": 1,
		"Pätzold": 1,
		"Raisky": 1,
		"Rakhimov": 1,
		"Rakhmanin": 1,
		"Rakhmanov": 1,
		"Rakhmatullayev": 1,
		"Ramazanov": 1,
		"Reshetko": 3,
		"Reshetnev": 2,
		"Rifel": 1,
		"Rodionov": 3,
		"Rogovskoy": 1,
		"Romashkin": 1,
		"Roskhrest": 1,
		"Royev": 1,
		"Rozhnov": 1,
		"Rublyov": 1,
		"Rumyantsev": 1,
		"Ruslan": 1,
		"Ruslanuly": 1,
		"Ruzbakiyev": 1,
		"Ryabchikov": 1,
		"Ryashin": 1,
		"Ryazanov": 1,
		"Rybin": 1,
		"Rymarev": 1,
		"Rysbekov": 2,
		"Ryzhy": 1,
		"Sadikov": 1,
		"Sadykov": 1,
		"Safronov": 1,
		"Sagadeyev": 1,
		"Sagymbayev": 2,
		"Saiko": 1,
		"Sailau": 1,
		"Samarov": 1,
		"Sanarov": 1,
		"Saparbek": 1,
		"Sapargaliyev": 1,
		"Sarkenov": 2,
		"Sarsembayev": 1,
		"Sarsikeyev": 1,
		"Saruarbek": 1,
		"Satemirov": 1,
		"Sattar": 1,
		"Savitsky": 1,
		"Sedov": 1,
		"Sekerbai": 1,
		"Seleznyov": 1,
		"Seliverstov": 2,
		"Selivyorstov": 2,
		"Semyonov": 1,
		"Sergeev": 1,
		"Sergeyev": 1,
		"Sergiyenko": 2,
		"Serik": 2,
		"Serikbulatov": 1,
		"Sevastyanov": 1,
		"Sevidov": 1,
		"Shafranov": 1,
		"Shaiikov": 1,
		"Shaikenov": 1,
		"Shaikhmeddenov": 1,
		"Shakenov": 1,
		"Shakhimurat": 1,
		"Shakshakbayev": 1,
		"Shakubayev": 1,
		"Shalapov": 1,
		"Shamky": 1,
		"Shaporov": 1,
		"Shaposhnik": 1,
		"Sharapov": 1,
		"Sharipov": 1,
		"Shayanov": 1,
		"Shefer": 1,
		"Shegebayev": 1,
		"Shemelin": 1,
		"Shemelturov": 1,
		"Shestakov": 2,
		"Shetle": 1,
		"Shevchenko": 3,
		"Shimin": 1,
		"Shin": 1,
		"Shinkovsky": 1,
		"Shipilin": 1,
		"Shipulin": 1,
		"Shipunov": 1,
		"Shishikin": 1,
		"Shishov": 1,
		"Shkenev": 1,
		"Shklennik": 1,
		"Shkondin": 1,
		"Shlychkov": 1,
		"Shlykov": 1,
		"Shmidt": 1,
		"Shpak": 1,
		"Shpigun": 1,
		"Shtefan": 1,
		"Shukelov": 1,
		"Shulga": 2,
		"Shutov": 1,
		"Sidorenko": 1,
		"Simakhin": 1,
		"Simeonidi": 1,
		"Simonov": 2,
		"Sindeyev": 1,
		"Sinkevich": 1,
		"Sitnikov": 1,
		"Sklyar": 1,
		"Skorykh": 4,
		"Slatin": 1,
		"Smaganbet": 1,
		"Smagulov": 1,
		"Smakov": 1,
		"Smelov": 1,
		"Smelyanets": 1,
		"Smolnikov": 1,
		"Smolyaninov": 1,
		"Snytin": 1,
		"Sokolov": 3,
		"Sokolovsky": 1,
		"Solovey": 1,
		"Sorochinskiy": 2,
		"Soshnikov": 1,
		"Spiridonov": 2,
		"Starchenko": 1,
		"Starinenko": 1,
		"Starygin": 1,
		"Stennikov": 1,
		"Stepanenko": 1,
		"Stepanov": 1,
		"Storchak": 1,
		"Suiumagambetov": 1,
		"Sukhodolsky": 1,
		"Suleimanov": 1,
		"Suleimenov": 1,
		"Surovtsev": 1,
		"Svedberg": 1,
		"Svintalsky": 1,
		"Svoyevolin": 1,
		"Tagner": 1,
		"Talerko": 1,
		"Tambulov": 1,
		"Tanirbergen": 1,
		"Tanzharikov": 3,
		"Tarada": 1,
		"Tarasov": 2,
		"Tasbulat": 1,
		"Tashimov": 2,
		"Tatarintsev": 1,
		"Telegin": 1,
		"Ten": 2,
		"Tikhonov": 2,
		"Timofeyev": 1,
		"Titov": 1,
		"Tkachyov": 1,
		"Tlenchiyev": 1,
		"Tleshev": 2,
		"Tleubayev": 1,
		"Tleukhan": 1,
		"Tokarev": 1,
		"Toktasynov": 1,
		"Toleubai": 1,
		"Tolstenev": 1,
		"Tolstunov": 1,
		"Toluspayev": 1,
		"Tregubov": 1,
		"Tribunsky": 1,
		"Trifonov": 1,
		"Tsapko": 1,
		"Tserulnikov": 1,
		"Tsikhotsky": 1,
		"Tsoi": 1,
		"Tsybin": 1,
		"Tukin": 1,
		"Tulemisov": 1,
		"Tursynov": 1,
		"Tusupbekov": 2,
		"Tuzov": 1,
		"Tyumentsev": 1,
		"Tyutyaev": 1,
		"Tyutyunkov": 1,
		"Umerenkov": 2,
		"Utebayev": 1,
		"Utepkaliyev": 1,
		"Uteyev": 1,
		"Vagner": 1,
		"Valentinov": 1,
		"Valentyukevich": 1,
		"Valikhanov": 1,
		"Valk": 1,
		"Vasilyev": 3,
		"Venetsky": 1,
		"Ventsel": 1,
		"Vereschagin": 1,
		"Volkov": 4,
		"Volosatov": 1,
		"Vorobyov": 3,
		"Vygovsky": 1,
		"Vysotsky": 1,
		"Yagovkin": 1,
		"Yakovenko": 2,
		"Yakovlev": 1,
		"Yakushev": 1,
		"Yankov": 1,
		"Yanuvarov": 1,
		"Yefimov": 1,
		"Yefremov": 1,
		"Yegorov": 1,
		"Yegupov": 1,
		"Yeldes": 1,
		"Yelemesov": 1,
		"Yelizarov": 1,
		"Yelkhimov": 1,
		"Yemelyanov": 2,
		"Yerasov": 1,
		"Yeremeyev": 1,
		"Yerkinov": 3,
		"Yermukhanov": 1,
		"Yershov": 1,
		"Yeserkepov": 1,
		"Yesimov": 1,
		"Yesirkenov": 1,
		"Yevdokimov": 1,
		"Yevloyev": 1,
		"Yevplov": 1,
		"Yrys": 1,
		"Yudin": 1,
		"Yugai": 1,
		"Yulbarisov": 1,
		"Zabrodin": 1,
		"Zaburdyayev": 1,
		"Zadorozhny": 1,
		"Zaidysh": 1,
		"Zainysh": 1,
		"Zakarlyukin": 1,
		"Zakaryanov": 1,
		"Zakharchenko": 1,
		"Zalevsky": 1,
		"Zarutsky": 1,
		"Zavyalov": 1,
		"Zdorovenko": 1,
		"Zemlyanoy": 1,
		"Zen'kovich": 2,
		"Zhabunin": 1,
		"Zhailauov": 1,
		"Zhaksylykov": 2,
		"Zhamanov": 1,
		"Zhanbolatuly": 1,
		"Zhanibekov": 1,
		"Zhantasov": 1,
		"Zhdanovsky": 1,
		"Zhitkov": 1,
		"Zhumadildinov": 1,
		"Zhumagaliyev": 1,
		"Zhumakan": 1,
		"Zhumaskaliev": 6,
		"Zhumazhan": 1,
		"Zhurbin": 1,
		"Zhusupbekov": 1,
		"Zinovyev": 1,
		"Ziyash": 1,
		"Zizevskikh": 1,
		"Zlobin": 1,
		"Zubarev": 1,
		"Zubov": 2,
		"Zybin": 1,
		"Zyuzin": 1
	}
}